{
  "tid": 3,
  "teamName": "Appalachian State Mountaineers",
  "source": "TeamCrafters",
  "sourceUpdated": "2026-02-17",
  "parsedAt": "2026-05-31",
  "players": [
    {
      "name": "Rashod Dubinion",
      "firstName": "Rashod",
      "lastName": "Dubinion",
      "position": "HB",
      "jerseyNumber": "7",
      "height": "5'10\"",
      "weight": 210,
      "class": "Sr",
      "archetype": "Elusive Bruiser",
      "devTrait": "",
      "overall": 84,
      "abilities": [],
      "hometown": "",
      "state": ""
    },
    {
      "name": "Ethan Johnson",
      "firstName": "Ethan",
      "lastName": "Johnson",
      "position": "CB",
      "jerseyNumber": "2",
      "height": "5'11\"",
      "weight": 195,
      "class": "Sr",
      "archetype": "Bump and Run",
      "devTrait": "",
      "overall": 83,
      "abilities": [],
      "hometown": "",
      "state": ""
    },
    {
      "name": "Colton Phares",
      "firstName": "Colton",
      "lastName": "Phares",
      "position": "SAM",
      "jerseyNumber": "10",
      "height": "6'2\"",
      "weight": 225,
      "class": "RS So",
      "archetype": "Lurker",
      "devTrait": "",
      "overall": 83,
      "abilities": [],
      "hometown": "",
      "state": ""
    },
    {
      "name": "Jaquari Lewis",
      "firstName": "Jaquari",
      "lastName": "Lewis",
      "position": "HB",
      "jerseyNumber": "22",
      "height": "5'10\"",
      "weight": 205,
      "class": "Fr",
      "archetype": "East/West Playmaker",
      "devTrait": "",
      "overall": 82,
      "abilities": [],
      "hometown": "",
      "state": ""
    },
    {
      "name": "Izayah Cummings",
      "firstName": "Izayah",
      "lastName": "Cummings",
      "position": "TE",
      "jerseyNumber": "4",
      "height": "6'4\"",
      "weight": 240,
      "class": "RS Sr",
      "archetype": "Physical Route Runner",
      "devTrait": "",
      "overall": 81,
      "abilities": [],
      "hometown": "",
      "state": ""
    },
    {
      "name": "Kanye Roberts",
      "firstName": "Kanye",
      "lastName": "Roberts",
      "position": "HB",
      "jerseyNumber": "2",
      "height": "6'0\"",
      "weight": 205,
      "class": "RS Jr",
      "archetype": "East/West Playmaker",
      "devTrait": "",
      "overall": 80,
      "abilities": [],
      "hometown": "",
      "state": ""
    },
    {
      "name": "Jaden Barnes",
      "firstName": "Jaden",
      "lastName": "Barnes",
      "position": "WR",
      "jerseyNumber": "15",
      "height": "5'8\"",
      "weight": 170,
      "class": "Jr",
      "archetype": "Route Artist",
      "devTrait": "",
      "overall": 80,
      "abilities": [],
      "hometown": "",
      "state": ""
    },
    {
      "name": "Dalton Stroman",
      "firstName": "Dalton",
      "lastName": "Stroman",
      "position": "WR",
      "jerseyNumber": "8",
      "height": "6'4\"",
      "weight": 210,
      "class": "RS Sr",
      "archetype": "Speedster",
      "devTrait": "",
      "overall": 79,
      "abilities": [],
      "hometown": "",
      "state": ""
    },
    {
      "name": "David Larkins",
      "firstName": "David",
      "lastName": "Larkins",
      "position": "TE",
      "jerseyNumber": "85",
      "height": "6'5\"",
      "weight": 250,
      "class": "RS Sr",
      "archetype": "Physical Route Runner",
      "devTrait": "",
      "overall": 79,
      "abilities": [
        "Sure Hands"
      ],
      "hometown": "",
      "state": ""
    },
    {
      "name": "Emory Floyd",
      "firstName": "Emory",
      "lastName": "Floyd",
      "position": "CB",
      "jerseyNumber": "6",
      "height": "6'1\"",
      "weight": 195,
      "class": "RS Jr",
      "archetype": "Zone",
      "devTrait": "",
      "overall": 78,
      "abilities": [],
      "hometown": "",
      "state": ""
    },
    {
      "name": "Jayden Ramsey",
      "firstName": "Jayden",
      "lastName": "Ramsey",
      "position": "LT",
      "jerseyNumber": "63",
      "height": "6'6\"",
      "weight": 300,
      "class": "RS Sr",
      "archetype": "Raw Strength",
      "devTrait": "",
      "overall": 78,
      "abilities": [],
      "hometown": "",
      "state": ""
    },
    {
      "name": "Khalifa Keith",
      "firstName": "Khalifa",
      "lastName": "Keith",
      "position": "HB",
      "jerseyNumber": "18",
      "height": "6'1\"",
      "weight": 235,
      "class": "RS So",
      "archetype": "Elusive Bruiser",
      "devTrait": "",
      "overall": 78,
      "abilities": [
        "Headfirst",
        "Arm Bar"
      ],
      "hometown": "",
      "state": ""
    },
    {
      "name": "AJ Swann",
      "firstName": "AJ",
      "lastName": "Swann",
      "position": "QB",
      "jerseyNumber": "5",
      "height": "6'2\"",
      "weight": 220,
      "class": "RS Jr",
      "archetype": "Pocket Passer",
      "devTrait": "",
      "overall": 77,
      "abilities": [],
      "hometown": "",
      "state": ""
    },
    {
      "name": "Cayden Sweatt",
      "firstName": "Cayden",
      "lastName": "Sweatt",
      "position": "LG",
      "jerseyNumber": "52",
      "height": "6'4\"",
      "weight": 295,
      "class": "So",
      "archetype": "Pass Protector",
      "devTrait": "",
      "overall": 77,
      "abilities": [],
      "hometown": "",
      "state": ""
    },
    {
      "name": "Ja'Den McBurrows",
      "firstName": "Ja'Den",
      "lastName": "McBurrows",
      "position": "CB",
      "jerseyNumber": "18",
      "height": "5'11\"",
      "weight": 195,
      "class": "RS Sr",
      "archetype": "Zone",
      "devTrait": "",
      "overall": 77,
      "abilities": [],
      "hometown": "",
      "state": ""
    },
    {
      "name": "Nick Campbell",
      "firstName": "Nick",
      "lastName": "Campbell",
      "position": "DT",
      "jerseyNumber": "45",
      "height": "6'4\"",
      "weight": 290,
      "class": "RS Jr",
      "archetype": "Pure Power",
      "devTrait": "",
      "overall": 76,
      "abilities": [],
      "hometown": "",
      "state": ""
    },
    {
      "name": "Griffin Scroggs",
      "firstName": "Griffin",
      "lastName": "Scroggs",
      "position": "RG",
      "jerseyNumber": "74",
      "height": "6'3\"",
      "weight": 330,
      "class": "Jr",
      "archetype": "Raw Strength",
      "devTrait": "",
      "overall": 76,
      "abilities": [],
      "hometown": "",
      "state": ""
    },
    {
      "name": "Davion Dozier",
      "firstName": "Davion",
      "lastName": "Dozier",
      "position": "WR",
      "jerseyNumber": "1",
      "height": "6'4\"",
      "weight": 205,
      "class": "RS So",
      "archetype": "Speedster",
      "devTrait": "",
      "overall": 76,
      "abilities": [],
      "hometown": "",
      "state": ""
    },
    {
      "name": "Kevin Abrams-Verwayne",
      "firstName": "Kevin",
      "lastName": "Abrams-Verwayne",
      "position": "REDG",
      "jerseyNumber": "97",
      "height": "6'3\"",
      "weight": 245,
      "class": "RS Sr",
      "archetype": "Speed Rusher",
      "devTrait": "",
      "overall": 76,
      "abilities": [],
      "hometown": "",
      "state": ""
    },
    {
      "name": "Elijah Mc-Cantos",
      "firstName": "Elijah",
      "lastName": "Mc-Cantos",
      "position": "FS",
      "jerseyNumber": "13",
      "height": "6'0\"",
      "weight": 190,
      "class": "Jr",
      "archetype": "Hybrid",
      "devTrait": "",
      "overall": 76,
      "abilities": [],
      "hometown": "",
      "state": ""
    },
    {
      "name": "Kyle Arnholt",
      "firstName": "Kyle",
      "lastName": "Arnholt",
      "position": "MIKE",
      "jerseyNumber": "56",
      "height": "6'2\"",
      "weight": 225,
      "class": "RS Sr",
      "archetype": "Signal Caller",
      "devTrait": "",
      "overall": 76,
      "abilities": [],
      "hometown": "",
      "state": ""
    },
    {
      "name": "JJ Kohl",
      "firstName": "JJ",
      "lastName": "Kohl",
      "position": "QB",
      "jerseyNumber": "17",
      "height": "6'7\"",
      "weight": 245,
      "class": "RS So",
      "archetype": "Pocket Passer",
      "devTrait": "",
      "overall": 76,
      "abilities": [],
      "hometown": "",
      "state": ""
    },
    {
      "name": "Zyeir Gamble",
      "firstName": "Zyeir",
      "lastName": "Gamble",
      "position": "FS",
      "jerseyNumber": "5",
      "height": "5'10\"",
      "weight": 195,
      "class": "RS So",
      "archetype": "Box Specialist",
      "devTrait": "",
      "overall": 76,
      "abilities": [],
      "hometown": "",
      "state": ""
    },
    {
      "name": "Shamarr Jackson",
      "firstName": "Shamarr",
      "lastName": "Jackson",
      "position": "RT",
      "jerseyNumber": "55",
      "height": "6'3\"",
      "weight": 295,
      "class": "RS Sr",
      "archetype": "Pass Protector",
      "devTrait": "",
      "overall": 75,
      "abilities": [],
      "hometown": "",
      "state": ""
    },
    {
      "name": "Shawn Collins",
      "firstName": "Shawn",
      "lastName": "Collins",
      "position": "LEDG",
      "jerseyNumber": "1",
      "height": "6'5\"",
      "weight": 265,
      "class": "RS Sr",
      "archetype": "Power Rusher",
      "devTrait": "",
      "overall": 75,
      "abilities": [],
      "hometown": "",
      "state": ""
    },
    {
      "name": "Dominic De Freitas",
      "firstName": "Dominic",
      "lastName": "De Freitas",
      "position": "K",
      "jerseyNumber": "90",
      "height": "6'0\"",
      "weight": 190,
      "class": "Fr",
      "archetype": "Power",
      "devTrait": "",
      "overall": 75,
      "abilities": [],
      "hometown": "",
      "state": ""
    },
    {
      "name": "Will Flowers",
      "firstName": "Will",
      "lastName": "Flowers",
      "position": "C",
      "jerseyNumber": "73",
      "height": "6'3\"",
      "weight": 300,
      "class": "RS Sr",
      "archetype": "Pass Protector",
      "devTrait": "",
      "overall": 75,
      "abilities": [],
      "hometown": "",
      "state": ""
    },
    {
      "name": "Jordan Favors",
      "firstName": "Jordan",
      "lastName": "Favors",
      "position": "SS",
      "jerseyNumber": "7",
      "height": "5'11\"",
      "weight": 200,
      "class": "RS Sr",
      "archetype": "Hybrid",
      "devTrait": "",
      "overall": 74,
      "abilities": [],
      "hometown": "",
      "state": ""
    },
    {
      "name": "Tyriq Poindexter",
      "firstName": "Tyriq",
      "lastName": "Poindexter",
      "position": "RT",
      "jerseyNumber": "78",
      "height": "6'5\"",
      "weight": 310,
      "class": "RS Sr",
      "archetype": "Well Rounded",
      "devTrait": "",
      "overall": 74,
      "abilities": [],
      "hometown": "",
      "state": ""
    },
    {
      "name": "Khamani Alexander",
      "firstName": "Khamani",
      "lastName": "Alexander",
      "position": "HB",
      "jerseyNumber": "26",
      "height": "6'1\"",
      "weight": 205,
      "class": "RS Fr",
      "archetype": "East/West Playmaker",
      "devTrait": "",
      "overall": 74,
      "abilities": [],
      "hometown": "",
      "state": ""
    },
    {
      "name": "Lance Williams",
      "firstName": "Lance",
      "lastName": "Williams",
      "position": "LG",
      "jerseyNumber": "68",
      "height": "6'3\"",
      "weight": 305,
      "class": "RS So",
      "archetype": "Raw Strength",
      "devTrait": "",
      "overall": 73,
      "abilities": [],
      "hometown": "",
      "state": ""
    },
    {
      "name": "Myles Farmer",
      "firstName": "Myles",
      "lastName": "Farmer",
      "position": "SS",
      "jerseyNumber": "4",
      "height": "6'3\"",
      "weight": 210,
      "class": "Sr",
      "archetype": "Box Specialist",
      "devTrait": "",
      "overall": 73,
      "abilities": [],
      "hometown": "",
      "state": ""
    },
    {
      "name": "Dylan Hasz",
      "firstName": "Dylan",
      "lastName": "Hasz",
      "position": "FS",
      "jerseyNumber": "8",
      "height": "5'11\"",
      "weight": 195,
      "class": "Jr",
      "archetype": "Box Specialist",
      "devTrait": "",
      "overall": 73,
      "abilities": [],
      "hometown": "",
      "state": ""
    },
    {
      "name": "Thomas Davis",
      "firstName": "Thomas",
      "lastName": "Davis",
      "position": "REDG",
      "jerseyNumber": "15",
      "height": "6'2\"",
      "weight": 240,
      "class": "Jr",
      "archetype": "Speed Rusher",
      "devTrait": "",
      "overall": 73,
      "abilities": [],
      "hometown": "",
      "state": ""
    },
    {
      "name": "DJ Burks",
      "firstName": "DJ",
      "lastName": "Burks",
      "position": "SS",
      "jerseyNumber": "21",
      "height": "6'0\"",
      "weight": 200,
      "class": "RS Jr",
      "archetype": "Coverage Specialist",
      "devTrait": "",
      "overall": 73,
      "abilities": [],
      "hometown": "",
      "state": ""
    },
    {
      "name": "Cristian Conyer",
      "firstName": "Cristian",
      "lastName": "Conyer",
      "position": "CB",
      "jerseyNumber": "24",
      "height": "6'1\"",
      "weight": 185,
      "class": "Jr",
      "archetype": "Zone",
      "devTrait": "",
      "overall": 73,
      "abilities": [],
      "hometown": "",
      "state": ""
    },
    {
      "name": "Rondarius Porter",
      "firstName": "Rondarius",
      "lastName": "Porter",
      "position": "DT",
      "jerseyNumber": "44",
      "height": "6'0\"",
      "weight": 295,
      "class": "RS Jr",
      "archetype": "Pure Power",
      "devTrait": "",
      "overall": 73,
      "abilities": [],
      "hometown": "",
      "state": ""
    },
    {
      "name": "Trent Ramsey",
      "firstName": "Trent",
      "lastName": "Ramsey",
      "position": "RG",
      "jerseyNumber": "67",
      "height": "6'5\"",
      "weight": 320,
      "class": "Jr",
      "archetype": "Pass Protector",
      "devTrait": "",
      "overall": 72,
      "abilities": [],
      "hometown": "",
      "state": ""
    },
    {
      "name": "Luke Burgess",
      "firstName": "Luke",
      "lastName": "Burgess",
      "position": "RT",
      "jerseyNumber": "76",
      "height": "6'8\"",
      "weight": 305,
      "class": "RS So",
      "archetype": "Pass Protector",
      "devTrait": "",
      "overall": 72,
      "abilities": [],
      "hometown": "",
      "state": ""
    },
    {
      "name": "Billy Wiles",
      "firstName": "Billy",
      "lastName": "Wiles",
      "position": "QB",
      "jerseyNumber": "9",
      "height": "6'3\"",
      "weight": 220,
      "class": "RS Sr",
      "archetype": "Backfield Creator",
      "devTrait": "",
      "overall": 72,
      "abilities": [],
      "hometown": "",
      "state": ""
    },
    {
      "name": "Juan Berchal",
      "firstName": "Juan",
      "lastName": "Berchal",
      "position": "CB",
      "jerseyNumber": "11",
      "height": "5'10\"",
      "weight": 185,
      "class": "Fr",
      "archetype": "Boundary",
      "devTrait": "",
      "overall": 72,
      "abilities": [],
      "hometown": "",
      "state": ""
    },
    {
      "name": "Dylan Manuel",
      "firstName": "Dylan",
      "lastName": "Manuel",
      "position": "DT",
      "jerseyNumber": "9",
      "height": "6'1\"",
      "weight": 300,
      "class": "So",
      "archetype": "Pure Power",
      "devTrait": "",
      "overall": 72,
      "abilities": [],
      "hometown": "",
      "state": ""
    },
    {
      "name": "William Fowles",
      "firstName": "William",
      "lastName": "Fowles",
      "position": "WR",
      "jerseyNumber": "12",
      "height": "6'3\"",
      "weight": 205,
      "class": "So",
      "archetype": "Speedster",
      "devTrait": "",
      "overall": 71,
      "abilities": [],
      "hometown": "",
      "state": ""
    },
    {
      "name": "Kanen Hamlett",
      "firstName": "Kanen",
      "lastName": "Hamlett",
      "position": "TE",
      "jerseyNumber": "86",
      "height": "6'4\"",
      "weight": 235,
      "class": "RS Jr",
      "archetype": "Physical Route Runner",
      "devTrait": "",
      "overall": 71,
      "abilities": [
        "Sure Hands"
      ],
      "hometown": "",
      "state": ""
    },
    {
      "name": "Brayshawn Littlejohn",
      "firstName": "Brayshawn",
      "lastName": "Littlejohn",
      "position": "SAM",
      "jerseyNumber": "12",
      "height": "6'0\"",
      "weight": 220,
      "class": "RS So",
      "archetype": "Signal Caller",
      "devTrait": "",
      "overall": 71,
      "abilities": [],
      "hometown": "",
      "state": ""
    },
    {
      "name": "Max Guest",
      "firstName": "Max",
      "lastName": "Guest",
      "position": "HB",
      "jerseyNumber": "31",
      "height": "5'9\"",
      "weight": 185,
      "class": "Fr",
      "archetype": "East/West Playmaker",
      "devTrait": "",
      "overall": 71,
      "abilities": [],
      "hometown": "",
      "state": ""
    },
    {
      "name": "Michael Marotta",
      "firstName": "Michael",
      "lastName": "Marotta",
      "position": "C",
      "jerseyNumber": "64",
      "height": "6'5\"",
      "weight": 295,
      "class": "RS Sr",
      "archetype": "Pass Protector",
      "devTrait": "",
      "overall": 70,
      "abilities": [],
      "hometown": "",
      "state": ""
    },
    {
      "name": "Jackson Moore",
      "firstName": "Jackson",
      "lastName": "Moore",
      "position": "K",
      "jerseyNumber": "39",
      "height": "5'10\"",
      "weight": 180,
      "class": "RS So",
      "archetype": "Power",
      "devTrait": "",
      "overall": 69,
      "abilities": [],
      "hometown": "",
      "state": ""
    },
    {
      "name": "Mitchell Lake",
      "firstName": "Mitchell",
      "lastName": "Lake",
      "position": "P",
      "jerseyNumber": "27",
      "height": "5'11\"",
      "weight": 200,
      "class": "RS So",
      "archetype": "Power",
      "devTrait": "",
      "overall": 69,
      "abilities": [],
      "hometown": "",
      "state": ""
    },
    {
      "name": "Cameren Fleming",
      "firstName": "Cameren",
      "lastName": "Fleming",
      "position": "SS",
      "jerseyNumber": "27",
      "height": "6'0\"",
      "weight": 195,
      "class": "RS So",
      "archetype": "Box Specialist",
      "devTrait": "",
      "overall": 69,
      "abilities": [],
      "hometown": "",
      "state": ""
    },
    {
      "name": "Alex Sanchez",
      "firstName": "Alex",
      "lastName": "Sanchez",
      "position": "WR",
      "jerseyNumber": "16",
      "height": "6'2\"",
      "weight": 195,
      "class": "Fr",
      "archetype": "Speedster",
      "devTrait": "",
      "overall": 69,
      "abilities": [],
      "hometown": "",
      "state": ""
    },
    {
      "name": "DeNigel Cooper",
      "firstName": "DeNigel",
      "lastName": "Cooper",
      "position": "DT",
      "jerseyNumber": "93",
      "height": "6'3\"",
      "weight": 260,
      "class": "Fr",
      "archetype": "Pure Power",
      "devTrait": "",
      "overall": 69,
      "abilities": [],
      "hometown": "",
      "state": ""
    },
    {
      "name": "Saint Farrior",
      "firstName": "Saint",
      "lastName": "Farrior",
      "position": "DT",
      "jerseyNumber": "96",
      "height": "6'3\"",
      "weight": 335,
      "class": "RS So",
      "archetype": "Pure Power",
      "devTrait": "",
      "overall": 69,
      "abilities": [],
      "hometown": "",
      "state": ""
    },
    {
      "name": "Ahmad Robinson",
      "firstName": "Ahmad",
      "lastName": "Robinson",
      "position": "CB",
      "jerseyNumber": "25",
      "height": "6'0\"",
      "weight": 180,
      "class": "RS Jr",
      "archetype": "Zone",
      "devTrait": "",
      "overall": 69,
      "abilities": [],
      "hometown": "",
      "state": ""
    },
    {
      "name": "Caleb Sandstrom",
      "firstName": "Caleb",
      "lastName": "Sandstrom",
      "position": "REDG",
      "jerseyNumber": "41",
      "height": "6'3\"",
      "weight": 250,
      "class": "RS So",
      "archetype": "Speed Rusher",
      "devTrait": "",
      "overall": 69,
      "abilities": [],
      "hometown": "",
      "state": ""
    },
    {
      "name": "Matthew Wilson",
      "firstName": "Matthew",
      "lastName": "Wilson",
      "position": "QB",
      "jerseyNumber": "6",
      "height": "6'0\"",
      "weight": 215,
      "class": "RS Fr",
      "archetype": "Backfield Creator",
      "devTrait": "",
      "overall": 68,
      "abilities": [],
      "hometown": "",
      "state": ""
    },
    {
      "name": "Jayden Bethea",
      "firstName": "Jayden",
      "lastName": "Bethea",
      "position": "MIKE",
      "jerseyNumber": "28",
      "height": "6'1\"",
      "weight": 230,
      "class": "RS So",
      "archetype": "Signal Caller",
      "devTrait": "",
      "overall": 68,
      "abilities": [],
      "hometown": "",
      "state": ""
    },
    {
      "name": "Noah Gillon",
      "firstName": "Noah",
      "lastName": "Gillon",
      "position": "QB",
      "jerseyNumber": "11",
      "height": "6'3\"",
      "weight": 195,
      "class": "Fr",
      "archetype": "Backfield Creator",
      "devTrait": "",
      "overall": 68,
      "abilities": [],
      "hometown": "",
      "state": ""
    },
    {
      "name": "Joseph Bakhole",
      "firstName": "Joseph",
      "lastName": "Bakhole",
      "position": "LEDG",
      "jerseyNumber": "3",
      "height": "6'2\"",
      "weight": 250,
      "class": "RS Sr",
      "archetype": "Speed Rusher",
      "devTrait": "",
      "overall": 68,
      "abilities": [],
      "hometown": "",
      "state": ""
    },
    {
      "name": "Bucci Farmer",
      "firstName": "Bucci",
      "lastName": "Farmer",
      "position": "DT",
      "jerseyNumber": "99",
      "height": "6'1\"",
      "weight": 310,
      "class": "RS Fr",
      "archetype": "Pure Power",
      "devTrait": "",
      "overall": 68,
      "abilities": [],
      "hometown": "",
      "state": ""
    },
    {
      "name": "Chris Lawson Jr.",
      "firstName": "Chris",
      "lastName": "Lawson Jr.",
      "position": "WR",
      "jerseyNumber": "82",
      "height": "6'0\"",
      "weight": 185,
      "class": "RS So",
      "archetype": "Elusive Route Runner",
      "devTrait": "",
      "overall": 68,
      "abilities": [],
      "hometown": "",
      "state": ""
    },
    {
      "name": "Gabriel Simpkins",
      "firstName": "Gabriel",
      "lastName": "Simpkins",
      "position": "TE",
      "jerseyNumber": "30",
      "height": "6'0\"",
      "weight": 220,
      "class": "RS So",
      "archetype": "Pure Blocker",
      "devTrait": "",
      "overall": 68,
      "abilities": [],
      "hometown": "",
      "state": ""
    },
    {
      "name": "Jaelin Willis",
      "firstName": "Jaelin",
      "lastName": "Willis",
      "position": "MIKE",
      "jerseyNumber": "0",
      "height": "6'0\"",
      "weight": 220,
      "class": "RS Sr",
      "archetype": "Lurker",
      "devTrait": "",
      "overall": 68,
      "abilities": [],
      "hometown": "",
      "state": ""
    },
    {
      "name": "Edward Coleman",
      "firstName": "Edward",
      "lastName": "Coleman",
      "position": "WR",
      "jerseyNumber": "0",
      "height": "5'11\"",
      "weight": 195,
      "class": "Fr",
      "archetype": "Speedster",
      "devTrait": "",
      "overall": 67,
      "abilities": [],
      "hometown": "",
      "state": ""
    },
    {
      "name": "Brooks Yurachek",
      "firstName": "Brooks",
      "lastName": "Yurachek",
      "position": "SAM",
      "jerseyNumber": "35",
      "height": "6'1\"",
      "weight": 220,
      "class": "RS So",
      "archetype": "Thumper",
      "devTrait": "",
      "overall": 67,
      "abilities": [],
      "hometown": "",
      "state": ""
    },
    {
      "name": "Danny Stevens",
      "firstName": "Danny",
      "lastName": "Stevens",
      "position": "RG",
      "jerseyNumber": "66",
      "height": "6'4\"",
      "weight": 295,
      "class": "RS So",
      "archetype": "Agile",
      "devTrait": "",
      "overall": 66,
      "abilities": [],
      "hometown": "",
      "state": ""
    },
    {
      "name": "Moritz Schmoranzer",
      "firstName": "Moritz",
      "lastName": "Schmoranzer",
      "position": "LG",
      "jerseyNumber": "54",
      "height": "6'4\"",
      "weight": 305,
      "class": "RS Fr",
      "archetype": "Agile",
      "devTrait": "",
      "overall": 66,
      "abilities": [],
      "hometown": "",
      "state": ""
    },
    {
      "name": "Kaden Ellis",
      "firstName": "Kaden",
      "lastName": "Ellis",
      "position": "DT",
      "jerseyNumber": "95",
      "height": "6'1\"",
      "weight": 295,
      "class": "Fr",
      "archetype": "Pure Power",
      "devTrait": "",
      "overall": 66,
      "abilities": [],
      "hometown": "",
      "state": ""
    },
    {
      "name": "Dillon Galloway",
      "firstName": "Dillon",
      "lastName": "Galloway",
      "position": "TE",
      "jerseyNumber": "87",
      "height": "6'4\"",
      "weight": 240,
      "class": "Fr",
      "archetype": "Pure Possession",
      "devTrait": "",
      "overall": 66,
      "abilities": [],
      "hometown": "",
      "state": ""
    },
    {
      "name": "Russell Rich",
      "firstName": "Russell",
      "lastName": "Rich",
      "position": "TE",
      "jerseyNumber": "89",
      "height": "6'6\"",
      "weight": 260,
      "class": "Jr",
      "archetype": "Vertical Threat",
      "devTrait": "",
      "overall": 65,
      "abilities": [],
      "hometown": "",
      "state": ""
    },
    {
      "name": "Jaylon Calhoun",
      "firstName": "Jaylon",
      "lastName": "Calhoun",
      "position": "HB",
      "jerseyNumber": "20",
      "height": "6'0\"",
      "weight": 200,
      "class": "RS So",
      "archetype": "East/West Playmaker",
      "devTrait": "",
      "overall": 65,
      "abilities": [],
      "hometown": "",
      "state": ""
    },
    {
      "name": "Kaleb Neal",
      "firstName": "Kaleb",
      "lastName": "Neal",
      "position": "FS",
      "jerseyNumber": "20",
      "height": "6'1\"",
      "weight": 195,
      "class": "RS Fr",
      "archetype": "Box Specialist",
      "devTrait": "",
      "overall": 65,
      "abilities": [],
      "hometown": "",
      "state": ""
    },
    {
      "name": "Ja'Torian Mack",
      "firstName": "Ja'Torian",
      "lastName": "Mack",
      "position": "SS",
      "jerseyNumber": "17",
      "height": "5'11\"",
      "weight": 190,
      "class": "Fr",
      "archetype": "Hybrid",
      "devTrait": "",
      "overall": 65,
      "abilities": [],
      "hometown": "",
      "state": ""
    },
    {
      "name": "Jared Gibble",
      "firstName": "Jared",
      "lastName": "Gibble",
      "position": "TE",
      "jerseyNumber": "44",
      "height": "6'4\"",
      "weight": 235,
      "class": "RS Sr",
      "archetype": "Physical Route Runner",
      "devTrait": "",
      "overall": 65,
      "abilities": [],
      "hometown": "",
      "state": ""
    },
    {
      "name": "Jackson Grier",
      "firstName": "Jackson",
      "lastName": "Grier",
      "position": "WR",
      "jerseyNumber": "13",
      "height": "5'11\"",
      "weight": 195,
      "class": "RS So",
      "archetype": "Speedster",
      "devTrait": "",
      "overall": 64,
      "abilities": [],
      "hometown": "",
      "state": ""
    },
    {
      "name": "Ronnie Porter",
      "firstName": "Ronnie",
      "lastName": "Porter",
      "position": "MIKE",
      "jerseyNumber": "22",
      "height": "6'0\"",
      "weight": 235,
      "class": "Sr",
      "archetype": "Signal Caller",
      "devTrait": "",
      "overall": 64,
      "abilities": [],
      "hometown": "",
      "state": ""
    },
    {
      "name": "K.J. Liles",
      "firstName": "K.J.",
      "lastName": "Liles",
      "position": "DT",
      "jerseyNumber": "51",
      "height": "6'1\"",
      "weight": 315,
      "class": "Fr",
      "archetype": "Pure Power",
      "devTrait": "",
      "overall": 64,
      "abilities": [],
      "hometown": "",
      "state": ""
    },
    {
      "name": "Tyshawn Sanders",
      "firstName": "Tyshawn",
      "lastName": "Sanders",
      "position": "CB",
      "jerseyNumber": "16",
      "height": "6'0\"",
      "weight": 180,
      "class": "RS Fr",
      "archetype": "Bump and Run",
      "devTrait": "",
      "overall": 63,
      "abilities": [],
      "hometown": "",
      "state": ""
    },
    {
      "name": "Ian Ratliff",
      "firstName": "Ian",
      "lastName": "Ratliff",
      "position": "P",
      "jerseyNumber": "37",
      "height": "5'11\"",
      "weight": 180,
      "class": "RS So",
      "archetype": "Power",
      "devTrait": "",
      "overall": 63,
      "abilities": [],
      "hometown": "",
      "state": ""
    },
    {
      "name": "Denell Nix Jr",
      "firstName": "Denell",
      "lastName": "Nix Jr",
      "position": "LT",
      "jerseyNumber": "72",
      "height": "6'5\"",
      "weight": 290,
      "class": "Fr",
      "archetype": "Raw Strength",
      "devTrait": "",
      "overall": 63,
      "abilities": [],
      "hometown": "",
      "state": ""
    },
    {
      "name": "Jacob Poff",
      "firstName": "Jacob",
      "lastName": "Poff",
      "position": "TE",
      "jerseyNumber": "47",
      "height": "6'0\"",
      "weight": 185,
      "class": "Fr",
      "archetype": "Pure Blocker",
      "devTrait": "",
      "overall": 63,
      "abilities": [],
      "hometown": "",
      "state": ""
    },
    {
      "name": "J.C. Falk",
      "firstName": "J.C.",
      "lastName": "Falk",
      "position": "LEDG",
      "jerseyNumber": "70",
      "height": "6'6\"",
      "weight": 264,
      "class": "Fr",
      "archetype": "Power Rusher",
      "devTrait": "",
      "overall": 62,
      "abilities": [],
      "hometown": "",
      "state": ""
    },
    {
      "name": "Caleb Pitts",
      "firstName": "Caleb",
      "lastName": "Pitts",
      "position": "REDG",
      "jerseyNumber": "94",
      "height": "6'2\"",
      "weight": 265,
      "class": "Fr",
      "archetype": "Power Rusher",
      "devTrait": "",
      "overall": 62,
      "abilities": [],
      "hometown": "",
      "state": ""
    },
    {
      "name": "Cash McVay",
      "firstName": "Cash",
      "lastName": "McVay",
      "position": "K",
      "jerseyNumber": "43",
      "height": "6'1\"",
      "weight": 180,
      "class": "RS Sr",
      "archetype": "Power",
      "devTrait": "",
      "overall": 62,
      "abilities": [],
      "hometown": "",
      "state": ""
    },
    {
      "name": "AJ Mebane",
      "firstName": "AJ",
      "lastName": "Mebane",
      "position": "WILL",
      "jerseyNumber": "92",
      "height": "6'3\"",
      "weight": 240,
      "class": "RS So",
      "archetype": "Thumper",
      "devTrait": "",
      "overall": 56,
      "abilities": [],
      "hometown": "",
      "state": ""
    }
  ]
}
