{
  "tid": 6,
  "teamName": "Army Black Knights",
  "source": "TeamCrafters",
  "sourceUpdated": "2026-02-17",
  "parsedAt": "2026-05-31",
  "players": [
    {
      "name": "Brady Small",
      "firstName": "Brady",
      "lastName": "Small",
      "position": "C",
      "jerseyNumber": "51",
      "height": "6'0\"",
      "weight": 315,
      "class": "Jr",
      "archetype": "Raw Strength",
      "devTrait": "",
      "overall": 89,
      "abilities": [
        "Workhorse",
        "Ground N Pound",
        "Inside Shield",
        "Adrenaline",
        "Fan Favorite",
        "Offensive Rally"
      ],
      "ratings": {
        "speed": 70,
        "strength": 91,
        "agility": 72,
        "accel": 78,
        "cod": 58,
        "injury": 95,
        "stamina": 93,
        "awareness": 94
      },
      "hometown": "",
      "state": ""
    },
    {
      "name": "Will Jeffcoat",
      "firstName": "Will",
      "lastName": "Jeffcoat",
      "position": "LG",
      "jerseyNumber": "59",
      "height": "6'2\"",
      "weight": 305,
      "class": "Sr",
      "archetype": "Raw Strength",
      "devTrait": "",
      "overall": 88,
      "abilities": [
        "Ground N Pound",
        "Second Level"
      ],
      "ratings": {
        "speed": 66,
        "strength": 90,
        "agility": 63,
        "accel": 74,
        "cod": 57,
        "injury": 85,
        "stamina": 85,
        "awareness": 90
      },
      "hometown": "",
      "state": ""
    },
    {
      "name": "Andon Thomas",
      "firstName": "Andon",
      "lastName": "Thomas",
      "position": "SAM",
      "jerseyNumber": "51",
      "height": "6'0\"",
      "weight": 230,
      "class": "Sr",
      "archetype": "Signal Caller",
      "devTrait": "",
      "overall": 84,
      "abilities": [],
      "ratings": {
        "speed": 83,
        "strength": 77,
        "agility": 79,
        "accel": 87,
        "cod": 77,
        "injury": 91,
        "stamina": 91,
        "awareness": 88
      },
      "hometown": "",
      "state": ""
    },
    {
      "name": "Noah Short",
      "firstName": "Noah",
      "lastName": "Short",
      "position": "WR",
      "jerseyNumber": "15",
      "height": "6'0\"",
      "weight": 195,
      "class": "Sr",
      "archetype": "Speedster",
      "devTrait": "",
      "overall": 83,
      "abilities": [],
      "ratings": {
        "speed": 92,
        "strength": 62,
        "agility": 86,
        "accel": 91,
        "cod": 86,
        "injury": 87,
        "stamina": 88,
        "awareness": 88
      },
      "hometown": "",
      "state": ""
    },
    {
      "name": "Hayden Reed",
      "firstName": "Hayden",
      "lastName": "Reed",
      "position": "HB",
      "jerseyNumber": "8",
      "height": "6'0\"",
      "weight": 220,
      "class": "Sr",
      "archetype": "Elusive Bruiser",
      "devTrait": "",
      "overall": 82,
      "abilities": [
        "Headfirst"
      ],
      "ratings": {
        "speed": 84,
        "strength": 82,
        "agility": 78,
        "accel": 87,
        "cod": 76,
        "injury": 91,
        "stamina": 96,
        "awareness": 87
      },
      "hometown": "",
      "state": ""
    },
    {
      "name": "Casey Larkin",
      "firstName": "Casey",
      "lastName": "Larkin",
      "position": "SS",
      "jerseyNumber": "20",
      "height": "6'0\"",
      "weight": 195,
      "class": "Sr",
      "archetype": "Box Specialist",
      "devTrait": "",
      "overall": 82,
      "abilities": [],
      "ratings": {
        "speed": 85,
        "strength": 64,
        "agility": 85,
        "accel": 86,
        "cod": 83,
        "injury": 93,
        "stamina": 92,
        "awareness": 87
      },
      "hometown": "",
      "state": ""
    },
    {
      "name": "Jaydan Mayes",
      "firstName": "Jaydan",
      "lastName": "Mayes",
      "position": "CB",
      "jerseyNumber": "7",
      "height": "5'10\"",
      "weight": 188,
      "class": "Jr",
      "archetype": "Zone",
      "devTrait": "",
      "overall": 82,
      "abilities": [],
      "ratings": {
        "speed": 90,
        "strength": 62,
        "agility": 90,
        "accel": 92,
        "cod": 88,
        "injury": 92,
        "stamina": 92,
        "awareness": 87
      },
      "hometown": "",
      "state": ""
    },
    {
      "name": "Kalib Fortner",
      "firstName": "Kalib",
      "lastName": "Fortner",
      "position": "MIKE",
      "jerseyNumber": "53",
      "height": "6'1\"",
      "weight": 220,
      "class": "Sr",
      "archetype": "Signal Caller",
      "devTrait": "",
      "overall": 81,
      "abilities": [
        "Workhorse",
        "Take Down",
        "Instinct"
      ],
      "ratings": {
        "speed": 83,
        "strength": 76,
        "agility": 80,
        "accel": 85,
        "cod": 77,
        "injury": 92,
        "stamina": 91,
        "awareness": 88
      },
      "hometown": "",
      "state": ""
    },
    {
      "name": "Justin Weaver",
      "firstName": "Justin",
      "lastName": "Weaver",
      "position": "CB",
      "jerseyNumber": "5",
      "height": "5'11\"",
      "weight": 190,
      "class": "Sr",
      "archetype": "Zone",
      "devTrait": "",
      "overall": 80,
      "abilities": [],
      "ratings": {
        "speed": 89,
        "strength": 63,
        "agility": 87,
        "accel": 92,
        "cod": 86,
        "injury": 91,
        "stamina": 88,
        "awareness": 83
      },
      "hometown": "",
      "state": ""
    },
    {
      "name": "Cale Hellums",
      "firstName": "Cale",
      "lastName": "Hellums",
      "position": "QB",
      "jerseyNumber": "3",
      "height": "5'10\"",
      "weight": 205,
      "class": "Jr",
      "archetype": "Pure Runner",
      "devTrait": "",
      "overall": 79,
      "abilities": [],
      "ratings": {
        "speed": 85,
        "strength": 70,
        "agility": 86,
        "accel": 87,
        "cod": 84,
        "injury": 88,
        "stamina": 91,
        "awareness": 82
      },
      "hometown": "",
      "state": ""
    },
    {
      "name": "Kody Harris-Miller",
      "firstName": "Kody",
      "lastName": "Harris-Miller",
      "position": "DT",
      "jerseyNumber": "52",
      "height": "6'1\"",
      "weight": 310,
      "class": "Jr",
      "archetype": "Pure Power",
      "devTrait": "",
      "overall": 79,
      "abilities": [],
      "ratings": {
        "speed": 66,
        "strength": 86,
        "agility": 62,
        "accel": 74,
        "cod": 55,
        "injury": 92,
        "stamina": 83,
        "awareness": 85
      },
      "hometown": "",
      "state": ""
    },
    {
      "name": "Jake Rendina",
      "firstName": "Jake",
      "lastName": "Rendina",
      "position": "FB",
      "jerseyNumber": "33",
      "height": "5'11\"",
      "weight": 240,
      "class": "Jr",
      "archetype": "Blocking",
      "devTrait": "",
      "overall": 79,
      "abilities": [],
      "ratings": {
        "speed": 79,
        "strength": 82,
        "agility": 74,
        "accel": 81,
        "cod": 71,
        "injury": 87,
        "stamina": 85,
        "awareness": 86
      },
      "hometown": "",
      "state": ""
    },
    {
      "name": "Collin Matteson",
      "firstName": "Collin",
      "lastName": "Matteson",
      "position": "FS",
      "jerseyNumber": "30",
      "height": "6'0\"",
      "weight": 195,
      "class": "Sr",
      "archetype": "Coverage Specialist",
      "devTrait": "",
      "overall": 78,
      "abilities": [],
      "ratings": {
        "speed": 87,
        "strength": 67,
        "agility": 85,
        "accel": 90,
        "cod": 83,
        "injury": 84,
        "stamina": 90,
        "awareness": 83
      },
      "hometown": "",
      "state": ""
    },
    {
      "name": "Jarel Dickson",
      "firstName": "Jarel",
      "lastName": "Dickson",
      "position": "FB",
      "jerseyNumber": "5",
      "height": "5'11\"",
      "weight": 214,
      "class": "Sr",
      "archetype": "Utility",
      "devTrait": "",
      "overall": 78,
      "abilities": [],
      "ratings": {
        "speed": 82,
        "strength": 77,
        "agility": 79,
        "accel": 85,
        "cod": 75,
        "injury": 88,
        "stamina": 85,
        "awareness": 83
      },
      "hometown": "",
      "state": ""
    },
    {
      "name": "Briggs Bartosh",
      "firstName": "Briggs",
      "lastName": "Bartosh",
      "position": "HB",
      "jerseyNumber": "29",
      "height": "5'10\"",
      "weight": 213,
      "class": "RS So",
      "archetype": "East/West Playmaker",
      "devTrait": "",
      "overall": 78,
      "abilities": [],
      "ratings": {
        "speed": 87,
        "strength": 71,
        "agility": 86,
        "accel": 91,
        "cod": 85,
        "injury": 91,
        "stamina": 86,
        "awareness": 75
      },
      "hometown": "",
      "state": ""
    },
    {
      "name": "Trey Tremba",
      "firstName": "Trey",
      "lastName": "Tremba",
      "position": "HB",
      "jerseyNumber": "16",
      "height": "5'10\"",
      "weight": 200,
      "class": "So",
      "archetype": "East/West Playmaker",
      "devTrait": "",
      "overall": 77,
      "abilities": [],
      "ratings": {
        "speed": 88,
        "strength": 66,
        "agility": 85,
        "accel": 92,
        "cod": 84,
        "injury": 82,
        "stamina": 81,
        "awareness": 71
      },
      "hometown": "",
      "state": ""
    },
    {
      "name": "Jack Latore",
      "firstName": "Jack",
      "lastName": "Latore",
      "position": "LEDG",
      "jerseyNumber": "92",
      "height": "6'5\"",
      "weight": 290,
      "class": "Sr",
      "archetype": "Pure Power",
      "devTrait": "",
      "overall": 77,
      "abilities": [],
      "ratings": {
        "speed": 71,
        "strength": 81,
        "agility": 67,
        "accel": 77,
        "cod": 63,
        "injury": 93,
        "stamina": 76,
        "awareness": 85
      },
      "hometown": "",
      "state": ""
    },
    {
      "name": "Jack Bousum",
      "firstName": "Jack",
      "lastName": "Bousum",
      "position": "REDG",
      "jerseyNumber": "99",
      "height": "6'4\"",
      "weight": 268,
      "class": "So",
      "archetype": "Power Rusher",
      "devTrait": "",
      "overall": 77,
      "abilities": [],
      "ratings": {
        "speed": 78,
        "strength": 79,
        "agility": 76,
        "accel": 84,
        "cod": 71,
        "injury": 87,
        "stamina": 76,
        "awareness": 80
      },
      "hometown": "",
      "state": ""
    },
    {
      "name": "Braden Bartosh",
      "firstName": "Braden",
      "lastName": "Bartosh",
      "position": "RG",
      "jerseyNumber": "50",
      "height": "6'2\"",
      "weight": 305,
      "class": "Sr",
      "archetype": "Agile",
      "devTrait": "",
      "overall": 76,
      "abilities": [],
      "ratings": {
        "speed": 60,
        "strength": 89,
        "agility": 55,
        "accel": 72,
        "cod": 54,
        "injury": 86,
        "stamina": 85,
        "awareness": 75
      },
      "hometown": "",
      "state": ""
    },
    {
      "name": "Aden Self",
      "firstName": "Aden",
      "lastName": "Self",
      "position": "HB",
      "jerseyNumber": "2",
      "height": "5'11\"",
      "weight": 220,
      "class": "So",
      "archetype": "Elusive Bruiser",
      "devTrait": "",
      "overall": 76,
      "abilities": [
        "Headfirst"
      ],
      "ratings": {
        "speed": 85,
        "strength": 80,
        "agility": 81,
        "accel": 87,
        "cod": 80,
        "injury": 89,
        "stamina": 79,
        "awareness": 72
      },
      "hometown": "",
      "state": ""
    },
    {
      "name": "Gavin Shields",
      "firstName": "Gavin",
      "lastName": "Shields",
      "position": "FS",
      "jerseyNumber": "14",
      "height": "6'2\"",
      "weight": 205,
      "class": "Sr",
      "archetype": "Box Specialist",
      "devTrait": "",
      "overall": 76,
      "abilities": [],
      "ratings": {
        "speed": 83,
        "strength": 75,
        "agility": 83,
        "accel": 85,
        "cod": 81,
        "injury": 90,
        "stamina": 91,
        "awareness": 85
      },
      "hometown": "",
      "state": ""
    },
    {
      "name": "Stephen Nnadozie",
      "firstName": "Stephen",
      "lastName": "Nnadozie",
      "position": "SS",
      "jerseyNumber": "3",
      "height": "5'11\"",
      "weight": 190,
      "class": "Jr",
      "archetype": "Coverage Specialist",
      "devTrait": "",
      "overall": 75,
      "abilities": [],
      "ratings": {
        "speed": 88,
        "strength": 63,
        "agility": 85,
        "accel": 91,
        "cod": 80,
        "injury": 88,
        "stamina": 90,
        "awareness": 76
      },
      "hometown": "",
      "state": ""
    },
    {
      "name": "Dewayne Coleman",
      "firstName": "Dewayne",
      "lastName": "Coleman",
      "position": "QB",
      "jerseyNumber": "10",
      "height": "5'10\"",
      "weight": 200,
      "class": "Sr",
      "archetype": "Pure Runner",
      "devTrait": "",
      "overall": 75,
      "abilities": [],
      "ratings": {
        "speed": 85,
        "strength": 61,
        "agility": 86,
        "accel": 88,
        "cod": 85,
        "injury": 87,
        "stamina": 95,
        "awareness": 75
      },
      "hometown": "",
      "state": ""
    },
    {
      "name": "Isaiah Birl",
      "firstName": "Isaiah",
      "lastName": "Birl",
      "position": "WILL",
      "jerseyNumber": "36",
      "height": "6'0\"",
      "weight": 220,
      "class": "Sr",
      "archetype": "Lurker",
      "devTrait": "",
      "overall": 75,
      "abilities": [],
      "ratings": {
        "speed": 83,
        "strength": 66,
        "agility": 78,
        "accel": 86,
        "cod": 76,
        "injury": 92,
        "stamina": 90,
        "awareness": 78
      },
      "hometown": "",
      "state": ""
    },
    {
      "name": "Eric Ford",
      "firstName": "Eric",
      "lastName": "Ford",
      "position": "LEDG",
      "jerseyNumber": "40",
      "height": "6'3\"",
      "weight": 235,
      "class": "Sr",
      "archetype": "Speed Rusher",
      "devTrait": "",
      "overall": 74,
      "abilities": [],
      "ratings": {
        "speed": 77,
        "strength": 81,
        "agility": 77,
        "accel": 84,
        "cod": 73,
        "injury": 87,
        "stamina": 81,
        "awareness": 81
      },
      "hometown": "",
      "state": ""
    },
    {
      "name": "CJ Martin",
      "firstName": "CJ",
      "lastName": "Martin",
      "position": "CB",
      "jerseyNumber": "4",
      "height": "5'11\"",
      "weight": 190,
      "class": "So",
      "archetype": "Boundary",
      "devTrait": "",
      "overall": 74,
      "abilities": [],
      "ratings": {
        "speed": 86,
        "strength": 62,
        "agility": 85,
        "accel": 90,
        "cod": 84,
        "injury": 88,
        "stamina": 91,
        "awareness": 80
      },
      "hometown": "",
      "state": ""
    },
    {
      "name": "Liam Fortner",
      "firstName": "Liam",
      "lastName": "Fortner",
      "position": "WR",
      "jerseyNumber": "4",
      "height": "6'1\"",
      "weight": 210,
      "class": "Sr",
      "archetype": "Route Artist",
      "devTrait": "",
      "overall": 72,
      "abilities": [],
      "ratings": {
        "speed": 86,
        "strength": 70,
        "agility": 85,
        "accel": 87,
        "cod": 84,
        "injury": 90,
        "stamina": 89,
        "awareness": 85
      },
      "hometown": "",
      "state": ""
    },
    {
      "name": "Zach Mundell",
      "firstName": "Zach",
      "lastName": "Mundell",
      "position": "QB",
      "jerseyNumber": "1",
      "height": "5'9\"",
      "weight": 185,
      "class": "Jr",
      "archetype": "Pure Runner",
      "devTrait": "",
      "overall": 72,
      "abilities": [
        "Workhorse"
      ],
      "ratings": {
        "speed": 82,
        "strength": 57,
        "agility": 85,
        "accel": 88,
        "cod": 83,
        "injury": 84,
        "stamina": 89,
        "awareness": 73
      },
      "hometown": "",
      "state": ""
    },
    {
      "name": "Tobi Olawole",
      "firstName": "Tobi",
      "lastName": "Olawole",
      "position": "WR",
      "jerseyNumber": "11",
      "height": "6'1\"",
      "weight": 200,
      "class": "Jr",
      "archetype": "Speedster",
      "devTrait": "",
      "overall": 72,
      "abilities": [],
      "ratings": {
        "speed": 91,
        "strength": 67,
        "agility": 89,
        "accel": 92,
        "cod": 87,
        "injury": 80,
        "stamina": 85,
        "awareness": 78
      },
      "hometown": "",
      "state": ""
    },
    {
      "name": "Deshontez Gray",
      "firstName": "Deshontez",
      "lastName": "Gray",
      "position": "REDG",
      "jerseyNumber": "98",
      "height": "6'3\"",
      "weight": 265,
      "class": "Sr",
      "archetype": "Pure Power",
      "devTrait": "",
      "overall": 72,
      "abilities": [],
      "ratings": {
        "speed": 71,
        "strength": 80,
        "agility": 73,
        "accel": 79,
        "cod": 69,
        "injury": 89,
        "stamina": 81,
        "awareness": 82
      },
      "hometown": "",
      "state": ""
    },
    {
      "name": "Ned Brady",
      "firstName": "Ned",
      "lastName": "Brady",
      "position": "LT",
      "jerseyNumber": "73",
      "height": "6'4\"",
      "weight": 300,
      "class": "Sr",
      "archetype": "Well Rounded",
      "devTrait": "",
      "overall": 72,
      "abilities": [],
      "ratings": {
        "speed": 64,
        "strength": 85,
        "agility": 57,
        "accel": 71,
        "cod": 53,
        "injury": 92,
        "stamina": 83,
        "awareness": 87
      },
      "hometown": "",
      "state": ""
    },
    {
      "name": "Tanner Bivins",
      "firstName": "Tanner",
      "lastName": "Bivins",
      "position": "RG",
      "jerseyNumber": "54",
      "height": "6'1\"",
      "weight": 300,
      "class": "Sr",
      "archetype": "Agile",
      "devTrait": "",
      "overall": 71,
      "abilities": [],
      "ratings": {
        "speed": 61,
        "strength": 87,
        "agility": 71,
        "accel": 75,
        "cod": 59,
        "injury": 83,
        "stamina": 89,
        "awareness": 86
      },
      "hometown": "",
      "state": ""
    },
    {
      "name": "Jacob Tuioti",
      "firstName": "Jacob",
      "lastName": "Tuioti",
      "position": "DT",
      "jerseyNumber": "62",
      "height": "6'1\"",
      "weight": 302,
      "class": "Sr",
      "archetype": "Pure Power",
      "devTrait": "",
      "overall": 71,
      "abilities": [],
      "ratings": {
        "speed": 65,
        "strength": 81,
        "agility": 64,
        "accel": 73,
        "cod": 52,
        "injury": 92,
        "stamina": 87,
        "awareness": 79
      },
      "hometown": "",
      "state": ""
    },
    {
      "name": "Lane Parks",
      "firstName": "Lane",
      "lastName": "Parks",
      "position": "RG",
      "jerseyNumber": "72",
      "height": "6'3\"",
      "weight": 305,
      "class": "Jr",
      "archetype": "Raw Strength",
      "devTrait": "",
      "overall": 71,
      "abilities": [],
      "ratings": {
        "speed": 58,
        "strength": 88,
        "agility": 56,
        "accel": 67,
        "cod": 50,
        "injury": 90,
        "stamina": 81,
        "awareness": 79
      },
      "hometown": "",
      "state": ""
    },
    {
      "name": "Samari Howard",
      "firstName": "Samari",
      "lastName": "Howard",
      "position": "WR",
      "jerseyNumber": "27",
      "height": "5'7\"",
      "weight": 190,
      "class": "Jr",
      "archetype": "Elusive Route Runner",
      "devTrait": "",
      "overall": 71,
      "abilities": [],
      "ratings": {
        "speed": 89,
        "strength": 60,
        "agility": 87,
        "accel": 92,
        "cod": 85,
        "injury": 75,
        "stamina": 83,
        "awareness": 82
      },
      "hometown": "",
      "state": ""
    },
    {
      "name": "Jaxon Hammond",
      "firstName": "Jaxon",
      "lastName": "Hammond",
      "position": "CB",
      "jerseyNumber": "17",
      "height": "5'10\"",
      "weight": 175,
      "class": "Jr",
      "archetype": "Bump and Run",
      "devTrait": "",
      "overall": 71,
      "abilities": [],
      "ratings": {
        "speed": 92,
        "strength": 53,
        "agility": 91,
        "accel": 94,
        "cod": 89,
        "injury": 81,
        "stamina": 97,
        "awareness": 70
      },
      "hometown": "",
      "state": ""
    },
    {
      "name": "Christopher Williams",
      "firstName": "Christopher",
      "lastName": "Williams",
      "position": "FS",
      "jerseyNumber": "32",
      "height": "5'9\"",
      "weight": 205,
      "class": "Jr",
      "archetype": "Coverage Specialist",
      "devTrait": "",
      "overall": 71,
      "abilities": [],
      "ratings": {
        "speed": 84,
        "strength": 59,
        "agility": 83,
        "accel": 87,
        "cod": 82,
        "injury": 88,
        "stamina": 86,
        "awareness": 75
      },
      "hometown": "",
      "state": ""
    },
    {
      "name": "Tyler Lee",
      "firstName": "Tyler",
      "lastName": "Lee",
      "position": "LG",
      "jerseyNumber": "56",
      "height": "6'1\"",
      "weight": 315,
      "class": "Jr",
      "archetype": "Raw Strength",
      "devTrait": "",
      "overall": 71,
      "abilities": [],
      "ratings": {
        "speed": 61,
        "strength": 87,
        "agility": 55,
        "accel": 69,
        "cod": 50,
        "injury": 92,
        "stamina": 94,
        "awareness": 76
      },
      "hometown": "",
      "state": ""
    },
    {
      "name": "Dawson Jones",
      "firstName": "Dawson",
      "lastName": "Jones",
      "position": "K",
      "jerseyNumber": "95",
      "height": "5'11\"",
      "weight": 190,
      "class": "So",
      "archetype": "Power",
      "devTrait": "",
      "overall": 71,
      "abilities": [],
      "ratings": {
        "speed": 62,
        "strength": 53,
        "agility": 64,
        "accel": 63,
        "cod": 54,
        "injury": 85,
        "stamina": 82,
        "awareness": 60
      },
      "hometown": "",
      "state": ""
    },
    {
      "name": "Brandon Wraalstad",
      "firstName": "Brandon",
      "lastName": "Wraalstad",
      "position": "RG",
      "jerseyNumber": "64",
      "height": "6'3\"",
      "weight": 281,
      "weightFixed": true,
      "class": "Jr",
      "archetype": "Well Rounded",
      "devTrait": "",
      "overall": 70,
      "abilities": [],
      "ratings": {
        "speed": 65,
        "strength": 82,
        "agility": 70,
        "accel": 75,
        "cod": 57,
        "injury": 81,
        "stamina": 93,
        "awareness": 75
      },
      "hometown": "",
      "state": ""
    },
    {
      "name": "Ethan Washington",
      "firstName": "Ethan",
      "lastName": "Washington",
      "position": "QB",
      "jerseyNumber": "9",
      "height": "6'1\"",
      "weight": 205,
      "class": "So",
      "archetype": "Pure Runner",
      "devTrait": "",
      "overall": 69,
      "abilities": [
        "Workhorse"
      ],
      "ratings": {
        "speed": 83,
        "strength": 59,
        "agility": 83,
        "accel": 87,
        "cod": 83,
        "injury": 87,
        "stamina": 95,
        "awareness": 65
      },
      "hometown": "",
      "state": ""
    },
    {
      "name": "AJ Williams",
      "firstName": "AJ",
      "lastName": "Williams",
      "position": "FB",
      "jerseyNumber": "65",
      "height": "6'0\"",
      "weight": 244,
      "class": "Sr",
      "archetype": "Utility",
      "devTrait": "",
      "overall": 69,
      "abilities": [],
      "ratings": {
        "speed": 73,
        "strength": 76,
        "agility": 77,
        "accel": 80,
        "cod": 75,
        "injury": 84,
        "stamina": 91,
        "awareness": 80
      },
      "hometown": "",
      "state": ""
    },
    {
      "name": "James Wagenseller",
      "firstName": "James",
      "lastName": "Wagenseller",
      "position": "P",
      "jerseyNumber": "46",
      "height": "6'3\"",
      "weight": 225,
      "class": "Jr",
      "archetype": "Power",
      "devTrait": "",
      "overall": 69,
      "abilities": [],
      "ratings": {
        "speed": 65,
        "strength": 68,
        "agility": 54,
        "accel": 65,
        "cod": 45,
        "injury": 90,
        "stamina": 85,
        "awareness": 60
      },
      "hometown": "",
      "state": ""
    },
    {
      "name": "Brady Mott",
      "firstName": "Brady",
      "lastName": "Mott",
      "position": "HB",
      "jerseyNumber": "18",
      "height": "6'1\"",
      "weight": 220,
      "class": "Jr",
      "archetype": "Elusive Bruiser",
      "devTrait": "",
      "overall": 69,
      "abilities": [],
      "ratings": {
        "speed": 84,
        "strength": 79,
        "agility": 83,
        "accel": 85,
        "cod": 79,
        "injury": 94,
        "stamina": 86,
        "awareness": 72
      },
      "hometown": "",
      "state": ""
    },
    {
      "name": "Kyle Kloska",
      "firstName": "Kyle",
      "lastName": "Kloska",
      "position": "C",
      "jerseyNumber": "75",
      "height": "6'3\"",
      "weight": 305,
      "class": "Jr",
      "archetype": "Agile",
      "devTrait": "",
      "overall": 69,
      "abilities": [],
      "ratings": {
        "speed": 65,
        "strength": 86,
        "agility": 60,
        "accel": 73,
        "cod": 55,
        "injury": 79,
        "stamina": 90,
        "awareness": 73
      },
      "hometown": "",
      "state": ""
    },
    {
      "name": "Christian Yousefzadeh",
      "firstName": "Christian",
      "lastName": "Yousefzadeh",
      "position": "REDG",
      "jerseyNumber": "49",
      "height": "6'3\"",
      "weight": 240,
      "class": "Jr",
      "archetype": "Speed Rusher",
      "devTrait": "",
      "overall": 68,
      "abilities": [],
      "ratings": {
        "speed": 79,
        "strength": 74,
        "agility": 76,
        "accel": 85,
        "cod": 68,
        "injury": 87,
        "stamina": 84,
        "awareness": 83
      },
      "hometown": "",
      "state": ""
    },
    {
      "name": "Parker Poloskey",
      "firstName": "Parker",
      "lastName": "Poloskey",
      "position": "TE",
      "jerseyNumber": "44",
      "height": "6'4\"",
      "weight": 250,
      "class": "Jr",
      "archetype": "Physical Route Runner",
      "devTrait": "",
      "overall": 68,
      "abilities": [],
      "ratings": {
        "speed": 77,
        "strength": 77,
        "agility": 75,
        "accel": 82,
        "cod": 72,
        "injury": 90,
        "stamina": 87,
        "awareness": 80
      },
      "hometown": "",
      "state": ""
    },
    {
      "name": "Todd Toby",
      "firstName": "Todd",
      "lastName": "Toby",
      "position": "LEDG",
      "jerseyNumber": "71",
      "height": "6'4\"",
      "weight": 249,
      "class": "Jr",
      "archetype": "Power Rusher",
      "devTrait": "",
      "overall": 67,
      "abilities": [],
      "ratings": {
        "speed": 69,
        "strength": 84,
        "agility": 70,
        "accel": 74,
        "cod": 63,
        "injury": 84,
        "stamina": 80,
        "awareness": 71
      },
      "hometown": "",
      "state": ""
    },
    {
      "name": "Baylor Newsom",
      "firstName": "Baylor",
      "lastName": "Newsom",
      "position": "SAM",
      "jerseyNumber": "21",
      "height": "6'1\"",
      "weight": 220,
      "class": "Jr",
      "archetype": "Thumper",
      "devTrait": "",
      "overall": 67,
      "abilities": [],
      "ratings": {
        "speed": 78,
        "strength": 72,
        "agility": 73,
        "accel": 82,
        "cod": 73,
        "injury": 91,
        "stamina": 87,
        "awareness": 77
      },
      "hometown": "",
      "state": ""
    },
    {
      "name": "Caleb Williams",
      "firstName": "Caleb",
      "lastName": "Williams",
      "position": "FS",
      "jerseyNumber": "13",
      "height": "5'10\"",
      "weight": 195,
      "class": "So",
      "archetype": "Box Specialist",
      "devTrait": "",
      "overall": 67,
      "abilities": [],
      "ratings": {
        "speed": 82,
        "strength": 61,
        "agility": 81,
        "accel": 86,
        "cod": 77,
        "injury": 91,
        "stamina": 85,
        "awareness": 69
      },
      "hometown": "",
      "state": ""
    },
    {
      "name": "Larry Pickett Jr.",
      "firstName": "Larry",
      "lastName": "Pickett Jr.",
      "position": "SS",
      "jerseyNumber": "22",
      "height": "6'1\"",
      "weight": 195,
      "class": "So",
      "archetype": "Coverage Specialist",
      "devTrait": "",
      "overall": 67,
      "abilities": [],
      "ratings": {
        "speed": 85,
        "strength": 58,
        "agility": 84,
        "accel": 87,
        "cod": 81,
        "injury": 85,
        "stamina": 86,
        "awareness": 70
      },
      "hometown": "",
      "state": ""
    },
    {
      "name": "Dillon Stowers",
      "firstName": "Dillon",
      "lastName": "Stowers",
      "position": "DT",
      "jerseyNumber": "96",
      "height": "6'2\"",
      "weight": 278,
      "weightFixed": true,
      "class": "Jr",
      "archetype": "Pure Power",
      "devTrait": "",
      "overall": 67,
      "abilities": [],
      "ratings": {
        "speed": 69,
        "strength": 74,
        "agility": 66,
        "accel": 78,
        "cod": 56,
        "injury": 82,
        "stamina": 94,
        "awareness": 75
      },
      "hometown": "",
      "state": ""
    },
    {
      "name": "Noah Nixon",
      "firstName": "Noah",
      "lastName": "Nixon",
      "position": "LEDG",
      "jerseyNumber": "47",
      "height": "6'2\"",
      "weight": 227,
      "class": "Jr",
      "archetype": "Edge Setter",
      "devTrait": "",
      "overall": 66,
      "abilities": [],
      "ratings": {
        "speed": 77,
        "strength": 72,
        "agility": 76,
        "accel": 82,
        "cod": 73,
        "injury": 92,
        "stamina": 80,
        "awareness": 79
      },
      "hometown": "",
      "state": ""
    },
    {
      "name": "Ish Taylor",
      "firstName": "Ish",
      "lastName": "Taylor",
      "position": "CB",
      "jerseyNumber": "25",
      "height": "5'9\"",
      "weight": 185,
      "class": "So",
      "archetype": "Boundary",
      "devTrait": "",
      "overall": 66,
      "abilities": [],
      "ratings": {
        "speed": 85,
        "strength": 59,
        "agility": 86,
        "accel": 88,
        "cod": 84,
        "injury": 83,
        "stamina": 89,
        "awareness": 71
      },
      "hometown": "",
      "state": ""
    },
    {
      "name": "Caden Brungard",
      "firstName": "Caden",
      "lastName": "Brungard",
      "position": "MIKE",
      "jerseyNumber": "31",
      "height": "6'0\"",
      "weight": 210,
      "class": "Jr",
      "archetype": "Lurker",
      "devTrait": "",
      "overall": 66,
      "abilities": [],
      "ratings": {
        "speed": 81,
        "strength": 66,
        "agility": 78,
        "accel": 84,
        "cod": 74,
        "injury": 86,
        "stamina": 84,
        "awareness": 74
      },
      "hometown": "",
      "state": ""
    },
    {
      "name": "Carson Smith",
      "firstName": "Carson",
      "lastName": "Smith",
      "position": "HB",
      "jerseyNumber": "34",
      "height": "6'0\"",
      "weight": 240,
      "class": "Jr",
      "archetype": "North/South Receiver",
      "devTrait": "",
      "overall": 66,
      "abilities": [],
      "ratings": {
        "speed": 80,
        "strength": 81,
        "agility": 79,
        "accel": 85,
        "cod": 78,
        "injury": 88,
        "stamina": 83,
        "awareness": 70
      },
      "hometown": "",
      "state": ""
    },
    {
      "name": "Cole Searight",
      "firstName": "Cole",
      "lastName": "Searight",
      "position": "CB",
      "jerseyNumber": "10",
      "height": "5'10\"",
      "weight": 195,
      "class": "So",
      "archetype": "Field",
      "devTrait": "",
      "overall": 66,
      "abilities": [],
      "ratings": {
        "speed": 84,
        "strength": 55,
        "agility": 86,
        "accel": 86,
        "cod": 82,
        "injury": 85,
        "stamina": 86,
        "awareness": 73
      },
      "hometown": "",
      "state": ""
    },
    {
      "name": "Brian Dyer",
      "firstName": "Brian",
      "lastName": "Dyer",
      "position": "TE",
      "jerseyNumber": "80",
      "height": "6'4\"",
      "weight": 245,
      "class": "Jr",
      "archetype": "Physical Route Runner",
      "devTrait": "",
      "overall": 66,
      "abilities": [],
      "ratings": {
        "speed": 75,
        "strength": 68,
        "agility": 77,
        "accel": 79,
        "cod": 74,
        "injury": 88,
        "stamina": 93,
        "awareness": 65
      },
      "hometown": "",
      "state": ""
    },
    {
      "name": "Cael Newton",
      "firstName": "Cael",
      "lastName": "Newton",
      "position": "REDG",
      "jerseyNumber": "97",
      "height": "6'5\"",
      "weight": 265,
      "class": "So",
      "archetype": "Speed Rusher",
      "devTrait": "",
      "overall": 66,
      "abilities": [],
      "ratings": {
        "speed": 75,
        "strength": 73,
        "agility": 72,
        "accel": 84,
        "cod": 66,
        "injury": 88,
        "stamina": 84,
        "awareness": 72
      },
      "hometown": "",
      "state": ""
    },
    {
      "name": "Lavar Thompson",
      "firstName": "Lavar",
      "lastName": "Thompson",
      "position": "RT",
      "jerseyNumber": "67",
      "height": "6'6\"",
      "weight": 299,
      "class": "Jr",
      "archetype": "Agile",
      "devTrait": "",
      "overall": 65,
      "abilities": [],
      "ratings": {
        "speed": 65,
        "strength": 78,
        "agility": 78,
        "accel": 82,
        "cod": 60,
        "injury": 83,
        "stamina": 96,
        "awareness": 82
      },
      "hometown": "",
      "state": ""
    },
    {
      "name": "Matt Board",
      "firstName": "Matt",
      "lastName": "Board",
      "position": "C",
      "jerseyNumber": "63",
      "height": "6'4\"",
      "weight": 290,
      "class": "Sr",
      "archetype": "Agile",
      "devTrait": "",
      "overall": 65,
      "abilities": [],
      "ratings": {
        "speed": 66,
        "strength": 77,
        "agility": 79,
        "accel": 83,
        "cod": 52,
        "injury": 81,
        "stamina": 91,
        "awareness": 73
      },
      "hometown": "",
      "state": ""
    },
    {
      "name": "Robert Houston",
      "firstName": "Robert",
      "lastName": "Houston",
      "position": "CB",
      "jerseyNumber": "9",
      "height": "5'10\"",
      "weight": 180,
      "class": "So",
      "archetype": "Field",
      "devTrait": "",
      "overall": 65,
      "abilities": [],
      "ratings": {
        "speed": 89,
        "strength": 47,
        "agility": 87,
        "accel": 91,
        "cod": 85,
        "injury": 89,
        "stamina": 83,
        "awareness": 67
      },
      "hometown": "",
      "state": ""
    },
    {
      "name": "Anderson Britton",
      "firstName": "Anderson",
      "lastName": "Britton",
      "position": "K",
      "jerseyNumber": "1",
      "height": "5'9\"",
      "weight": 180,
      "class": "Sr",
      "archetype": "Power",
      "devTrait": "",
      "overall": 65,
      "abilities": [],
      "ratings": {
        "speed": 57,
        "strength": 49,
        "agility": 54,
        "accel": 56,
        "cod": 51,
        "injury": 82,
        "stamina": 87,
        "awareness": 52
      },
      "hometown": "",
      "state": ""
    },
    {
      "name": "Jabril Williams",
      "firstName": "Jabril",
      "lastName": "Williams",
      "position": "CB",
      "jerseyNumber": "6",
      "height": "5'10\"",
      "weight": 190,
      "class": "Sr",
      "archetype": "Bump and Run",
      "devTrait": "",
      "overall": 65,
      "abilities": [],
      "ratings": {
        "speed": 87,
        "strength": 58,
        "agility": 85,
        "accel": 90,
        "cod": 83,
        "injury": 85,
        "stamina": 87,
        "awareness": 72
      },
      "hometown": "",
      "state": ""
    },
    {
      "name": "Devan Moss",
      "firstName": "Devan",
      "lastName": "Moss",
      "position": "CB",
      "jerseyNumber": "18",
      "height": "5'8\"",
      "weight": 177,
      "class": "So",
      "archetype": "Field",
      "devTrait": "",
      "overall": 65,
      "abilities": [],
      "ratings": {
        "speed": 87,
        "strength": 45,
        "agility": 86,
        "accel": 89,
        "cod": 83,
        "injury": 85,
        "stamina": 86,
        "awareness": 69
      },
      "hometown": "",
      "state": ""
    },
    {
      "name": "Brennan Fisher",
      "firstName": "Brennan",
      "lastName": "Fisher",
      "position": "MIKE",
      "jerseyNumber": "38",
      "height": "5'11\"",
      "weight": 230,
      "class": "So",
      "archetype": "Thumper",
      "devTrait": "",
      "overall": 65,
      "abilities": [],
      "ratings": {
        "speed": 75,
        "strength": 75,
        "agility": 74,
        "accel": 78,
        "cod": 74,
        "injury": 88,
        "stamina": 79,
        "awareness": 73
      },
      "hometown": "",
      "state": ""
    },
    {
      "name": "Michael Hales",
      "firstName": "Michael",
      "lastName": "Hales",
      "position": "LT",
      "jerseyNumber": "79",
      "height": "6'6\"",
      "weight": 310,
      "class": "Sr",
      "archetype": "Agile",
      "devTrait": "",
      "overall": 64,
      "abilities": [],
      "ratings": {
        "speed": 68,
        "strength": 78,
        "agility": 79,
        "accel": 83,
        "cod": 56,
        "injury": 82,
        "stamina": 93,
        "awareness": 67
      },
      "hometown": "",
      "state": ""
    },
    {
      "name": "Phil Timmerman",
      "firstName": "Phil",
      "lastName": "Timmerman",
      "position": "LG",
      "jerseyNumber": "74",
      "height": "6'3\"",
      "weight": 298,
      "class": "Jr",
      "archetype": "Agile",
      "devTrait": "",
      "overall": 64,
      "abilities": [
        "Quick Step"
      ],
      "ratings": {
        "speed": 66,
        "strength": 77,
        "agility": 79,
        "accel": 83,
        "cod": 58,
        "injury": 82,
        "stamina": 98,
        "awareness": 72
      },
      "hometown": "",
      "state": ""
    },
    {
      "name": "Cooper Allan",
      "firstName": "Cooper",
      "lastName": "Allan",
      "position": "P",
      "jerseyNumber": "38",
      "height": "6'1\"",
      "weight": 217,
      "class": "Sr",
      "archetype": "Power",
      "devTrait": "",
      "overall": 64,
      "abilities": [],
      "ratings": {
        "speed": 66,
        "strength": 51,
        "agility": 55,
        "accel": 59,
        "cod": 51,
        "injury": 89,
        "stamina": 85,
        "awareness": 50
      },
      "hometown": "",
      "state": ""
    },
    {
      "name": "Randy Farris",
      "firstName": "Randy",
      "lastName": "Farris",
      "position": "TE",
      "jerseyNumber": "81",
      "height": "6'3\"",
      "weight": 235,
      "class": "So",
      "archetype": "Physical Route Runner",
      "devTrait": "",
      "overall": 64,
      "abilities": [],
      "ratings": {
        "speed": 73,
        "strength": 72,
        "agility": 75,
        "accel": 79,
        "cod": 72,
        "injury": 82,
        "stamina": 95,
        "awareness": 60
      },
      "hometown": "",
      "state": ""
    },
    {
      "name": "Daniel Ogordi",
      "firstName": "Daniel",
      "lastName": "Ogordi",
      "position": "SS",
      "jerseyNumber": "37",
      "height": "6'1\"",
      "weight": 200,
      "class": "RS So",
      "archetype": "Coverage Specialist",
      "devTrait": "",
      "overall": 64,
      "abilities": [],
      "ratings": {
        "speed": 84,
        "strength": 72,
        "agility": 82,
        "accel": 86,
        "cod": 79,
        "injury": 82,
        "stamina": 87,
        "awareness": 62
      },
      "hometown": "",
      "state": ""
    },
    {
      "name": "Lance Van Lewan",
      "firstName": "Lance",
      "lastName": "Van Lewan",
      "position": "CB",
      "jerseyNumber": "24",
      "height": "5'11\"",
      "weight": 175,
      "class": "So",
      "archetype": "Bump and Run",
      "devTrait": "",
      "overall": 63,
      "abilities": [],
      "ratings": {
        "speed": 88,
        "strength": 55,
        "agility": 86,
        "accel": 90,
        "cod": 88,
        "injury": 85,
        "stamina": 90,
        "awareness": 53
      },
      "hometown": "",
      "state": ""
    },
    {
      "name": "Sean Donovan",
      "firstName": "Sean",
      "lastName": "Donovan",
      "position": "LEDG",
      "jerseyNumber": "91",
      "height": "6'1\"",
      "weight": 288,
      "weightFixed": true,
      "class": "So",
      "archetype": "Pure Power",
      "devTrait": "",
      "overall": 63,
      "abilities": [],
      "ratings": {
        "speed": 70,
        "strength": 81,
        "agility": 66,
        "accel": 76,
        "cod": 64,
        "injury": 87,
        "stamina": 87,
        "awareness": 71
      },
      "hometown": "",
      "state": ""
    },
    {
      "name": "Nick Hadley",
      "firstName": "Nick",
      "lastName": "Hadley",
      "position": "RT",
      "jerseyNumber": "78",
      "height": "6'5\"",
      "weight": 301,
      "class": "So",
      "archetype": "Agile",
      "devTrait": "",
      "overall": 61,
      "abilities": [],
      "ratings": {
        "speed": 56,
        "strength": 86,
        "agility": 71,
        "accel": 69,
        "cod": 52,
        "injury": 89,
        "stamina": 83,
        "awareness": 75
      },
      "hometown": "",
      "state": ""
    },
    {
      "name": "Desmond Franklin",
      "firstName": "Desmond",
      "lastName": "Franklin",
      "position": "DT",
      "jerseyNumber": "76",
      "height": "6'2\"",
      "weight": 296,
      "class": "Fr",
      "archetype": "Pure Power",
      "devTrait": "",
      "overall": 60,
      "abilities": [],
      "ratings": {
        "speed": 63,
        "strength": 84,
        "agility": 65,
        "accel": 75,
        "cod": 53,
        "injury": 83,
        "stamina": 88,
        "awareness": 75
      },
      "hometown": "",
      "state": ""
    },
    {
      "name": "Zaire Holt-Spencer",
      "firstName": "Zaire",
      "lastName": "Holt-Spencer",
      "position": "TE",
      "jerseyNumber": "82",
      "height": "6'4\"",
      "weight": 228,
      "class": "Fr",
      "archetype": "Vertical Threat",
      "devTrait": "",
      "overall": 59,
      "abilities": [],
      "ratings": {
        "speed": 74,
        "strength": 69,
        "agility": 79,
        "accel": 84,
        "cod": 74,
        "injury": 79,
        "stamina": 88,
        "awareness": 60
      },
      "hometown": "",
      "state": ""
    },
    {
      "name": "Joseph Benson",
      "firstName": "Joseph",
      "lastName": "Benson",
      "position": "MIKE",
      "jerseyNumber": "41",
      "height": "5'10\"",
      "weight": 223,
      "class": "Fr",
      "archetype": "Lurker",
      "devTrait": "",
      "overall": 58,
      "abilities": [],
      "ratings": {
        "speed": 79,
        "strength": 65,
        "agility": 83,
        "accel": 87,
        "cod": 81,
        "injury": 79,
        "stamina": 84,
        "awareness": 60
      },
      "hometown": "",
      "state": ""
    },
    {
      "name": "Peyton Clark",
      "firstName": "Peyton",
      "lastName": "Clark",
      "position": "DT",
      "jerseyNumber": "90",
      "height": "6'3\"",
      "weight": 288,
      "weightFixed": true,
      "class": "Fr",
      "archetype": "Gap Specialist",
      "devTrait": "",
      "overall": 58,
      "abilities": [],
      "ratings": {
        "speed": 65,
        "strength": 85,
        "agility": 65,
        "accel": 79,
        "cod": 55,
        "injury": 81,
        "stamina": 91,
        "awareness": 48
      },
      "hometown": "",
      "state": ""
    },
    {
      "name": "Lloyd Benson III",
      "firstName": "Lloyd",
      "lastName": "Benson III",
      "position": "WR",
      "jerseyNumber": "23",
      "height": "5'8\"",
      "weight": 195,
      "class": "Jr",
      "archetype": "Speedster",
      "devTrait": "",
      "overall": 58,
      "abilities": [],
      "ratings": {
        "speed": 87,
        "strength": 64,
        "agility": 87,
        "accel": 90,
        "cod": 85,
        "injury": 74,
        "stamina": 89,
        "awareness": 75
      },
      "hometown": "",
      "state": ""
    },
    {
      "name": "Wade Joiner",
      "firstName": "Wade",
      "lastName": "Joiner",
      "position": "LT",
      "jerseyNumber": "68",
      "height": "6'5\"",
      "weight": 294,
      "weightFixed": true,
      "class": "Fr",
      "archetype": "Agile",
      "devTrait": "",
      "overall": 58,
      "abilities": [],
      "ratings": {
        "speed": 72,
        "strength": 76,
        "agility": 79,
        "accel": 82,
        "cod": 60,
        "injury": 76,
        "stamina": 95,
        "awareness": 58
      },
      "hometown": "",
      "state": ""
    },
    {
      "name": "Drake Roberts",
      "firstName": "Drake",
      "lastName": "Roberts",
      "position": "WR",
      "jerseyNumber": "88",
      "height": "6'3\"",
      "weight": 195,
      "class": "Jr",
      "archetype": "Speedster",
      "devTrait": "",
      "overall": 57,
      "abilities": [],
      "ratings": {
        "speed": 90,
        "strength": 52,
        "agility": 90,
        "accel": 91,
        "cod": 91,
        "injury": 74,
        "stamina": 93,
        "awareness": 70
      },
      "hometown": "",
      "state": ""
    },
    {
      "name": "Duane Walker",
      "firstName": "Duane",
      "lastName": "Walker",
      "position": "LG",
      "jerseyNumber": "57",
      "height": "6'2\"",
      "weight": 283,
      "weightFixed": true,
      "class": "Fr",
      "archetype": "Agile",
      "devTrait": "",
      "overall": 57,
      "abilities": [],
      "ratings": {
        "speed": 60,
        "strength": 79,
        "agility": 74,
        "accel": 78,
        "cod": 55,
        "injury": 79,
        "stamina": 87,
        "awareness": 77
      },
      "hometown": "",
      "state": ""
    },
    {
      "name": "Shane Pelton",
      "firstName": "Shane",
      "lastName": "Pelton",
      "position": "C",
      "jerseyNumber": "61",
      "height": "6'2\"",
      "weight": 290,
      "weightFixed": true,
      "class": "Fr",
      "archetype": "Pass Protector",
      "devTrait": "",
      "overall": 57,
      "abilities": [],
      "ratings": {
        "speed": 60,
        "strength": 79,
        "agility": 75,
        "accel": 77,
        "cod": 55,
        "injury": 81,
        "stamina": 87,
        "awareness": 60
      },
      "hometown": "",
      "state": ""
    },
    {
      "name": "Kavon Pointer",
      "firstName": "Kavon",
      "lastName": "Pointer",
      "position": "WR",
      "jerseyNumber": "89",
      "height": "6'2\"",
      "weight": 215,
      "class": "Jr",
      "archetype": "Speedster",
      "devTrait": "",
      "overall": 56,
      "abilities": [],
      "ratings": {
        "speed": 82,
        "strength": 79,
        "agility": 82,
        "accel": 87,
        "cod": 78,
        "injury": 90,
        "stamina": 84,
        "awareness": 72
      },
      "hometown": "",
      "state": ""
    },
    {
      "name": "Owen Walter",
      "firstName": "Owen",
      "lastName": "Walter",
      "position": "TE",
      "jerseyNumber": "55",
      "height": "6'0\"",
      "weight": 225,
      "class": "Jr",
      "archetype": "Physical Route Runner",
      "devTrait": "",
      "overall": 55,
      "abilities": [],
      "ratings": {
        "speed": 70,
        "strength": 72,
        "agility": 74,
        "accel": 75,
        "cod": 71,
        "injury": 79,
        "stamina": 96,
        "awareness": 62
      },
      "hometown": "",
      "state": ""
    }
  ]
}
