{
  "tid": 72,
  "teamName": "New Mexico State Aggies",
  "source": "TeamCrafters",
  "sourceUpdated": "2026-02-17",
  "parsedAt": "2026-05-31",
  "players": [
    {
      "name": "Tyler Martinez",
      "firstName": "Tyler",
      "lastName": "Martinez",
      "position": "SAM",
      "jerseyNumber": "35",
      "height": "6'2\"",
      "weight": 225,
      "class": "Sr",
      "archetype": "Signal Caller",
      "devTrait": "",
      "overall": 85,
      "abilities": [
        "Take Down",
        "Instinct"
      ],
      "hometown": "",
      "state": ""
    },
    {
      "name": "Kadarius Calloway",
      "firstName": "Kadarius",
      "lastName": "Calloway",
      "position": "HB",
      "jerseyNumber": "1",
      "height": "6'0\"",
      "weight": 213,
      "class": "RS Sr",
      "archetype": "Elusive Bruiser",
      "devTrait": "",
      "overall": 82,
      "abilities": [
        "Headfirst",
        "Arm Bar",
        "Downhill"
      ],
      "hometown": "",
      "state": ""
    },
    {
      "name": "Dakerric Hobbs",
      "firstName": "Dakerric",
      "lastName": "Hobbs",
      "position": "CB",
      "jerseyNumber": "3",
      "height": "6'0\"",
      "weight": 195,
      "class": "RS Sr",
      "archetype": "Boundary",
      "devTrait": "",
      "overall": 82,
      "abilities": [],
      "hometown": "",
      "state": ""
    },
    {
      "name": "Ezra Christensen",
      "firstName": "Ezra",
      "lastName": "Christensen",
      "position": "DT",
      "jerseyNumber": "90",
      "height": "6'2\"",
      "weight": 260,
      "class": "Sr",
      "archetype": "Power Rusher",
      "devTrait": "",
      "overall": 82,
      "abilities": [],
      "hometown": "",
      "state": ""
    },
    {
      "name": "Donovan Faupel",
      "firstName": "Donovan",
      "lastName": "Faupel",
      "position": "WR",
      "jerseyNumber": "5",
      "height": "6'1\"",
      "weight": 195,
      "class": "Jr",
      "archetype": "Route Artist",
      "devTrait": "",
      "overall": 82,
      "abilities": [],
      "hometown": "",
      "state": ""
    },
    {
      "name": "Gavin Harris",
      "firstName": "Gavin",
      "lastName": "Harris",
      "position": "TE",
      "jerseyNumber": "2",
      "height": "6'3\"",
      "weight": 240,
      "class": "RS Jr",
      "archetype": "Physical Route Runner",
      "devTrait": "",
      "overall": 81,
      "abilities": [],
      "hometown": "",
      "state": ""
    },
    {
      "name": "Dijon Stanley",
      "firstName": "Dijon",
      "lastName": "Stanley",
      "position": "HB",
      "jerseyNumber": "8",
      "height": "6'0\"",
      "weight": 185,
      "class": "Jr",
      "archetype": "East/West Playmaker",
      "devTrait": "",
      "overall": 81,
      "abilities": [],
      "hometown": "",
      "state": ""
    },
    {
      "name": "Sone Aupiu",
      "firstName": "Sone",
      "lastName": "Aupiu",
      "position": "MIKE",
      "jerseyNumber": "14",
      "height": "6'1\"",
      "weight": 225,
      "class": "RS Jr",
      "archetype": "Signal Caller",
      "devTrait": "",
      "overall": 79,
      "abilities": [],
      "hometown": "",
      "state": ""
    },
    {
      "name": "Tyler King",
      "firstName": "Tyler",
      "lastName": "King",
      "position": "WR",
      "jerseyNumber": "12",
      "height": "5'9\"",
      "weight": 180,
      "class": "RS Jr",
      "archetype": "Speedster",
      "devTrait": "",
      "overall": 79,
      "abilities": [],
      "hometown": "",
      "state": ""
    },
    {
      "name": "Naeten Mitchell",
      "firstName": "Naeten",
      "lastName": "Mitchell",
      "position": "FS",
      "jerseyNumber": "4",
      "height": "5'11\"",
      "weight": 175,
      "class": "So",
      "archetype": "Coverage Specialist",
      "devTrait": "",
      "overall": 79,
      "abilities": [],
      "hometown": "",
      "state": ""
    },
    {
      "name": "Logan Fife",
      "firstName": "Logan",
      "lastName": "Fife",
      "position": "QB",
      "jerseyNumber": "4",
      "height": "6'0\"",
      "weight": 205,
      "class": "RS Sr",
      "archetype": "Backfield Creator",
      "devTrait": "",
      "overall": 79,
      "abilities": [],
      "hometown": "",
      "state": ""
    },
    {
      "name": "Gabe Peterson",
      "firstName": "Gabe",
      "lastName": "Peterson",
      "position": "LEDG",
      "jerseyNumber": "16",
      "height": "6'2\"",
      "weight": 255,
      "class": "RS Jr",
      "archetype": "Power Rusher",
      "devTrait": "",
      "overall": 78,
      "abilities": [],
      "hometown": "",
      "state": ""
    },
    {
      "name": "Nick Session",
      "firstName": "Nick",
      "lastName": "Session",
      "position": "SS",
      "jerseyNumber": "5",
      "height": "6'0\"",
      "weight": 190,
      "class": "RS Sr",
      "archetype": "Coverage Specialist",
      "devTrait": "",
      "overall": 78,
      "abilities": [],
      "hometown": "",
      "state": ""
    },
    {
      "name": "BJ Tolo",
      "firstName": "BJ",
      "lastName": "Tolo",
      "position": "RG",
      "jerseyNumber": "61",
      "height": "6'2\"",
      "weight": 310,
      "class": "RS So",
      "archetype": "Raw Strength",
      "devTrait": "",
      "overall": 78,
      "abilities": [
        "Pocket Shield"
      ],
      "hometown": "",
      "state": ""
    },
    {
      "name": "PJ Johnson III",
      "firstName": "PJ",
      "lastName": "Johnson III",
      "position": "WR",
      "jerseyNumber": "0",
      "height": "6'0\"",
      "weight": 190,
      "class": "RS Sr",
      "archetype": "Speedster",
      "devTrait": "",
      "overall": 76,
      "abilities": [],
      "hometown": "",
      "state": ""
    },
    {
      "name": "Armahn Hale",
      "firstName": "Armahn",
      "lastName": "Hale",
      "position": "SS",
      "jerseyNumber": "2",
      "height": "5'11\"",
      "weight": 195,
      "class": "Sr",
      "archetype": "Box Specialist",
      "devTrait": "",
      "overall": 75,
      "abilities": [],
      "hometown": "",
      "state": ""
    },
    {
      "name": "Ma'Kyi Lee",
      "firstName": "Ma'Kyi",
      "lastName": "Lee",
      "position": "LT",
      "jerseyNumber": "55",
      "height": "6'7\"",
      "weight": 315,
      "class": "RS Sr",
      "archetype": "Raw Strength",
      "devTrait": "",
      "overall": 75,
      "abilities": [],
      "hometown": "",
      "state": ""
    },
    {
      "name": "Cole Schnettgoecke",
      "firstName": "Cole",
      "lastName": "Schnettgoecke",
      "position": "DT",
      "jerseyNumber": "96",
      "height": "6'2\"",
      "weight": 300,
      "class": "RS Sr",
      "archetype": "Gap Specialist",
      "devTrait": "",
      "overall": 75,
      "abilities": [],
      "hometown": "",
      "state": ""
    },
    {
      "name": "Bernock Iya",
      "firstName": "Bernock",
      "lastName": "Iya",
      "position": "FS",
      "jerseyNumber": "9",
      "height": "6'2\"",
      "weight": 180,
      "class": "RS Jr",
      "archetype": "Coverage Specialist",
      "devTrait": "",
      "overall": 75,
      "abilities": [],
      "hometown": "",
      "state": ""
    },
    {
      "name": "Braydyn Sage",
      "firstName": "Braydyn",
      "lastName": "Sage",
      "position": "TE",
      "jerseyNumber": "41",
      "height": "6'0\"",
      "weight": 180,
      "class": "Fr",
      "archetype": "Pure Blocker",
      "devTrait": "",
      "overall": 75,
      "abilities": [],
      "hometown": "",
      "state": ""
    },
    {
      "name": "TJ Pride",
      "firstName": "TJ",
      "lastName": "Pride",
      "position": "WR",
      "jerseyNumber": "7",
      "height": "5'9\"",
      "weight": 170,
      "class": "So",
      "archetype": "Elusive Route Runner",
      "devTrait": "",
      "overall": 74,
      "abilities": [],
      "hometown": "",
      "state": ""
    },
    {
      "name": "DaQuan Hodge",
      "firstName": "DaQuan",
      "lastName": "Hodge",
      "position": "CB",
      "jerseyNumber": "48",
      "height": "6'2\"",
      "weight": 181,
      "class": "Jr",
      "archetype": "Boundary",
      "devTrait": "",
      "overall": 74,
      "abilities": [],
      "hometown": "",
      "state": ""
    },
    {
      "name": "Josiah Charles",
      "firstName": "Josiah",
      "lastName": "Charles",
      "position": "CB",
      "jerseyNumber": "1",
      "height": "6'0\"",
      "weight": 175,
      "class": "Jr",
      "archetype": "Boundary",
      "devTrait": "",
      "overall": 74,
      "abilities": [],
      "hometown": "",
      "state": ""
    },
    {
      "name": "Larenzo McMillan",
      "firstName": "Larenzo",
      "lastName": "McMillan",
      "position": "HB",
      "jerseyNumber": "16",
      "height": "5'10\"",
      "weight": 190,
      "class": "RS Sr",
      "archetype": "East/West Playmaker",
      "devTrait": "",
      "overall": 74,
      "abilities": [],
      "hometown": "",
      "state": ""
    },
    {
      "name": "Ryan Hawk",
      "firstName": "Ryan",
      "lastName": "Hawk",
      "position": "K",
      "jerseyNumber": "17",
      "height": "5'11\"",
      "weight": 165,
      "class": "RS Sr",
      "archetype": "Accurate",
      "devTrait": "",
      "overall": 74,
      "abilities": [],
      "hometown": "",
      "state": ""
    },
    {
      "name": "Parker Awad",
      "firstName": "Parker",
      "lastName": "Awad",
      "position": "QB",
      "jerseyNumber": "15",
      "height": "6'0\"",
      "weight": 195,
      "class": "Jr",
      "archetype": "Dual Threat",
      "devTrait": "",
      "overall": 73,
      "abilities": [],
      "hometown": "",
      "state": ""
    },
    {
      "name": "Armando Nieves",
      "firstName": "Armando",
      "lastName": "Nieves",
      "position": "RT",
      "jerseyNumber": "76",
      "height": "6'7\"",
      "weight": 315,
      "class": "RS Jr",
      "archetype": "Raw Strength",
      "devTrait": "",
      "overall": 73,
      "abilities": [],
      "hometown": "",
      "state": ""
    },
    {
      "name": "Jackson Owens",
      "firstName": "Jackson",
      "lastName": "Owens",
      "position": "WR",
      "jerseyNumber": "6",
      "height": "6'0\"",
      "weight": 200,
      "class": "RS Sr",
      "archetype": "Speedster",
      "devTrait": "",
      "overall": 73,
      "abilities": [],
      "hometown": "",
      "state": ""
    },
    {
      "name": "Will Kendricks",
      "firstName": "Will",
      "lastName": "Kendricks",
      "position": "CB",
      "jerseyNumber": "37",
      "height": "5'11\"",
      "weight": 179,
      "class": "So",
      "archetype": "Boundary",
      "devTrait": "",
      "overall": 72,
      "abilities": [],
      "hometown": "",
      "state": ""
    },
    {
      "name": "Martell Washington",
      "firstName": "Martell",
      "lastName": "Washington",
      "position": "HB",
      "jerseyNumber": "46",
      "height": "6'0\"",
      "weight": 201,
      "class": "Sr",
      "archetype": "Backfield Threat",
      "devTrait": "",
      "overall": 72,
      "abilities": [
        "Safety Valve"
      ],
      "hometown": "",
      "state": ""
    },
    {
      "name": "Tim Gans",
      "firstName": "Tim",
      "lastName": "Gans",
      "position": "HB",
      "jerseyNumber": "20",
      "height": "5'10\"",
      "weight": 195,
      "class": "RS Sr",
      "archetype": "East/West Playmaker",
      "devTrait": "",
      "overall": 72,
      "abilities": [],
      "hometown": "",
      "state": ""
    },
    {
      "name": "Obinna Okeke",
      "firstName": "Obinna",
      "lastName": "Okeke",
      "position": "REDG",
      "jerseyNumber": "25",
      "height": "6'3\"",
      "weight": 246,
      "class": "RS So",
      "archetype": "Speed Rusher",
      "devTrait": "",
      "overall": 72,
      "abilities": [],
      "hometown": "",
      "state": ""
    },
    {
      "name": "Jerry Lydiatt",
      "firstName": "Jerry",
      "lastName": "Lydiatt",
      "position": "TE",
      "jerseyNumber": "86",
      "height": "6'3\"",
      "weight": 240,
      "class": "RS So",
      "archetype": "Physical Route Runner",
      "devTrait": "",
      "overall": 72,
      "abilities": [],
      "hometown": "",
      "state": ""
    },
    {
      "name": "Josiah Jackson",
      "firstName": "Josiah",
      "lastName": "Jackson",
      "position": "DT",
      "jerseyNumber": "95",
      "height": "6'1\"",
      "weight": 290,
      "class": "RS Sr",
      "archetype": "Pure Power",
      "devTrait": "",
      "overall": 72,
      "abilities": [],
      "hometown": "",
      "state": ""
    },
    {
      "name": "Janik Ogunlade",
      "firstName": "Janik",
      "lastName": "Ogunlade",
      "position": "RT",
      "jerseyNumber": "73",
      "height": "6'5\"",
      "weight": 290,
      "class": "RS Sr",
      "archetype": "Well Rounded",
      "devTrait": "",
      "overall": 72,
      "abilities": [],
      "hometown": "",
      "state": ""
    },
    {
      "name": "Adam Parks",
      "firstName": "Adam",
      "lastName": "Parks",
      "position": "TE",
      "jerseyNumber": "84",
      "height": "6'4\"",
      "weight": 245,
      "class": "RS So",
      "archetype": "Physical Route Runner",
      "devTrait": "",
      "overall": 72,
      "abilities": [],
      "hometown": "",
      "state": ""
    },
    {
      "name": "Florian Staehler",
      "firstName": "Florian",
      "lastName": "Staehler",
      "position": "LG",
      "jerseyNumber": "79",
      "height": "6'7\"",
      "weight": 330,
      "class": "RS Sr",
      "archetype": "Pass Protector",
      "devTrait": "",
      "overall": 72,
      "abilities": [],
      "hometown": "",
      "state": ""
    },
    {
      "name": "Jaden Robinson",
      "firstName": "Jaden",
      "lastName": "Robinson",
      "position": "REDG",
      "jerseyNumber": "28",
      "height": "6'4\"",
      "weight": 225,
      "class": "RS Jr",
      "archetype": "Speed Rusher",
      "devTrait": "",
      "overall": 71,
      "abilities": [],
      "hometown": "",
      "state": ""
    },
    {
      "name": "Malik Williams",
      "firstName": "Malik",
      "lastName": "Williams",
      "position": "LT",
      "jerseyNumber": "78",
      "height": "6'4\"",
      "weight": 302,
      "class": "RS Sr",
      "archetype": "Raw Strength",
      "devTrait": "",
      "overall": 71,
      "abilities": [],
      "hometown": "",
      "state": ""
    },
    {
      "name": "Shawn Brown",
      "firstName": "Shawn",
      "lastName": "Brown",
      "position": "WR",
      "jerseyNumber": "3",
      "height": "6'3\"",
      "weight": 210,
      "class": "RS Sr",
      "archetype": "Speedster",
      "devTrait": "",
      "overall": 71,
      "abilities": [],
      "hometown": "",
      "state": ""
    },
    {
      "name": "AJ Williams III",
      "firstName": "AJ",
      "lastName": "Williams III",
      "position": "WR",
      "jerseyNumber": "11",
      "height": "6'4\"",
      "weight": 195,
      "class": "So",
      "archetype": "Speedster",
      "devTrait": "",
      "overall": 71,
      "abilities": [],
      "hometown": "",
      "state": ""
    },
    {
      "name": "Quincy Davis",
      "firstName": "Quincy",
      "lastName": "Davis",
      "position": "SAM",
      "jerseyNumber": "13",
      "height": "6'1\"",
      "weight": 230,
      "class": "Jr",
      "archetype": "Thumper",
      "devTrait": "",
      "overall": 71,
      "abilities": [],
      "hometown": "",
      "state": ""
    },
    {
      "name": "Max Dean",
      "firstName": "Max",
      "lastName": "Dean",
      "position": "P",
      "jerseyNumber": "32",
      "height": "6'1\"",
      "weight": 198,
      "class": "RS So",
      "archetype": "Power",
      "devTrait": "",
      "overall": 71,
      "abilities": [],
      "hometown": "",
      "state": ""
    },
    {
      "name": "Jamall Thompson Jr.",
      "firstName": "Jamall",
      "lastName": "Thompson Jr.",
      "position": "LEDG",
      "jerseyNumber": "6",
      "height": "6'3\"",
      "weight": 265,
      "class": "RS Sr",
      "archetype": "Power Rusher",
      "devTrait": "",
      "overall": 71,
      "abilities": [],
      "hometown": "",
      "state": ""
    },
    {
      "name": "Lukas Ungar",
      "firstName": "Lukas",
      "lastName": "Ungar",
      "position": "TE",
      "jerseyNumber": "89",
      "height": "6'4\"",
      "weight": 245,
      "class": "RS Sr",
      "archetype": "Physical Route Runner",
      "devTrait": "",
      "overall": 70,
      "abilities": [],
      "hometown": "",
      "state": ""
    },
    {
      "name": "Trevor Stephens",
      "firstName": "Trevor",
      "lastName": "Stephens",
      "position": "TE",
      "jerseyNumber": "88",
      "height": "6'3\"",
      "weight": 240,
      "class": "RS Jr",
      "archetype": "Physical Route Runner",
      "devTrait": "",
      "overall": 70,
      "abilities": [],
      "hometown": "",
      "state": ""
    },
    {
      "name": "Joshua Goines",
      "firstName": "Joshua",
      "lastName": "Goines",
      "position": "TE",
      "jerseyNumber": "18",
      "height": "6'3\"",
      "weight": 235,
      "class": "RS So",
      "archetype": "Vertical Threat",
      "devTrait": "",
      "overall": 70,
      "abilities": [],
      "hometown": "",
      "state": ""
    },
    {
      "name": "DJ Hill-Smith",
      "firstName": "DJ",
      "lastName": "Hill-Smith",
      "position": "FS",
      "jerseyNumber": "0",
      "height": "6'1\"",
      "weight": 180,
      "class": "Jr",
      "archetype": "Coverage Specialist",
      "devTrait": "",
      "overall": 70,
      "abilities": [],
      "hometown": "",
      "state": ""
    },
    {
      "name": "Tory Gethers",
      "firstName": "Tory",
      "lastName": "Gethers",
      "position": "MIKE",
      "jerseyNumber": "12",
      "height": "6'1\"",
      "weight": 215,
      "class": "Jr",
      "archetype": "Signal Caller",
      "devTrait": "",
      "overall": 70,
      "abilities": [],
      "hometown": "",
      "state": ""
    },
    {
      "name": "Larry Jones III",
      "firstName": "Larry",
      "lastName": "Jones III",
      "position": "LEDG",
      "jerseyNumber": "15",
      "height": "6'1\"",
      "weight": 250,
      "class": "Jr",
      "archetype": "Speed Rusher",
      "devTrait": "",
      "overall": 69,
      "abilities": [],
      "hometown": "",
      "state": ""
    },
    {
      "name": "Lanar Kelley Jr.",
      "firstName": "Lanar",
      "lastName": "Kelley Jr.",
      "position": "CB",
      "jerseyNumber": "22",
      "height": "5'10\"",
      "weight": 192,
      "class": "RS Sr",
      "archetype": "Boundary",
      "devTrait": "",
      "overall": 69,
      "abilities": [],
      "hometown": "",
      "state": ""
    },
    {
      "name": "Jaylen Patterson",
      "firstName": "Jaylen",
      "lastName": "Patterson",
      "position": "QB",
      "jerseyNumber": "10",
      "height": "6'1\"",
      "weight": 190,
      "class": "Fr",
      "archetype": "Dual Threat",
      "devTrait": "",
      "overall": 69,
      "abilities": [],
      "hometown": "",
      "state": ""
    },
    {
      "name": "Saveon Freeman",
      "firstName": "Saveon",
      "lastName": "Freeman",
      "position": "CB",
      "jerseyNumber": "7",
      "height": "6'0\"",
      "weight": 185,
      "class": "Jr",
      "archetype": "Boundary",
      "devTrait": "",
      "overall": 69,
      "abilities": [],
      "hometown": "",
      "state": ""
    },
    {
      "name": "Ta'Avili Tuitama",
      "firstName": "Ta'Avili",
      "lastName": "Tuitama",
      "position": "DT",
      "jerseyNumber": "54",
      "height": "6'2\"",
      "weight": 306,
      "class": "RS Jr",
      "archetype": "Pure Power",
      "devTrait": "",
      "overall": 69,
      "abilities": [],
      "hometown": "",
      "state": ""
    },
    {
      "name": "Mateo Rodriguez",
      "firstName": "Mateo",
      "lastName": "Rodriguez",
      "position": "LG",
      "jerseyNumber": "70",
      "height": "6'5\"",
      "weight": 305,
      "class": "RS Fr",
      "archetype": "Agile",
      "devTrait": "",
      "overall": 69,
      "abilities": [],
      "hometown": "",
      "state": ""
    },
    {
      "name": "Nicholas McGraw",
      "firstName": "Nicholas",
      "lastName": "McGraw",
      "position": "QB",
      "jerseyNumber": "18",
      "height": "6'3\"",
      "weight": 199,
      "class": "Fr",
      "archetype": "Backfield Creator",
      "devTrait": "",
      "overall": 68,
      "abilities": [],
      "hometown": "",
      "state": ""
    },
    {
      "name": "Walter Owens",
      "firstName": "Walter",
      "lastName": "Owens",
      "position": "FS",
      "jerseyNumber": "11",
      "height": "6'2\"",
      "weight": 195,
      "class": "Jr",
      "archetype": "Box Specialist",
      "devTrait": "",
      "overall": 68,
      "abilities": [],
      "hometown": "",
      "state": ""
    },
    {
      "name": "Enzo-Pierre Tayou",
      "firstName": "Enzo-Pierre",
      "lastName": "Tayou",
      "position": "DT",
      "jerseyNumber": "44",
      "height": "6'2\"",
      "weight": 288,
      "weightFixed": true,
      "class": "RS Jr",
      "archetype": "Pure Power",
      "devTrait": "",
      "overall": 68,
      "abilities": [],
      "hometown": "",
      "state": ""
    },
    {
      "name": "Henry Davis III",
      "firstName": "Henry",
      "lastName": "Davis III",
      "position": "DT",
      "jerseyNumber": "97",
      "height": "6'2\"",
      "weight": 288,
      "weightFixed": true,
      "class": "Jr",
      "archetype": "Power Rusher",
      "devTrait": "",
      "overall": 68,
      "abilities": [],
      "hometown": "",
      "state": ""
    },
    {
      "name": "Jabril White",
      "firstName": "Jabril",
      "lastName": "White",
      "position": "FS",
      "jerseyNumber": "19",
      "height": "5'10\"",
      "weight": 193,
      "class": "RS Sr",
      "archetype": "Coverage Specialist",
      "devTrait": "",
      "overall": 68,
      "abilities": [],
      "hometown": "",
      "state": ""
    },
    {
      "name": "Demanuel Brown Jr.",
      "firstName": "Demanuel",
      "lastName": "Brown Jr.",
      "position": "LEDG",
      "jerseyNumber": "30",
      "height": "6'2\"",
      "weight": 252,
      "class": "RS So",
      "archetype": "Speed Rusher",
      "devTrait": "",
      "overall": 67,
      "abilities": [],
      "hometown": "",
      "state": ""
    },
    {
      "name": "JR Hecklinski",
      "firstName": "JR",
      "lastName": "Hecklinski",
      "position": "LG",
      "jerseyNumber": "65",
      "height": "6'2\"",
      "weight": 288,
      "weightFixed": true,
      "class": "Fr",
      "archetype": "Well Rounded",
      "devTrait": "",
      "overall": 67,
      "abilities": [],
      "hometown": "",
      "state": ""
    },
    {
      "name": "Bradley Vislisel",
      "firstName": "Bradley",
      "lastName": "Vislisel",
      "position": "REDG",
      "jerseyNumber": "8",
      "height": "6'3\"",
      "weight": 240,
      "class": "RS So",
      "archetype": "Speed Rusher",
      "devTrait": "",
      "overall": 67,
      "abilities": [],
      "hometown": "",
      "state": ""
    },
    {
      "name": "Jakobe Campbell",
      "firstName": "Jakobe",
      "lastName": "Campbell",
      "position": "FS",
      "jerseyNumber": "26",
      "height": "6'0\"",
      "weight": 180,
      "class": "RS Fr",
      "archetype": "Coverage Specialist",
      "devTrait": "",
      "overall": 67,
      "abilities": [],
      "hometown": "",
      "state": ""
    },
    {
      "name": "Kai Wheeler",
      "firstName": "Kai",
      "lastName": "Wheeler",
      "position": "C",
      "jerseyNumber": "50",
      "height": "6'4\"",
      "weight": 300,
      "class": "RS So",
      "archetype": "Well Rounded",
      "devTrait": "",
      "overall": 66,
      "abilities": [],
      "hometown": "",
      "state": ""
    },
    {
      "name": "Hayden Harlan",
      "firstName": "Hayden",
      "lastName": "Harlan",
      "position": "LG",
      "jerseyNumber": "75",
      "height": "6'4\"",
      "weight": 295,
      "class": "RS Jr",
      "archetype": "Raw Strength",
      "devTrait": "",
      "overall": 66,
      "abilities": [],
      "hometown": "",
      "state": ""
    },
    {
      "name": "David Barker",
      "firstName": "David",
      "lastName": "Barker",
      "position": "P",
      "jerseyNumber": "92",
      "height": "6'0\"",
      "weight": 170,
      "class": "Fr",
      "archetype": "Accurate",
      "devTrait": "",
      "overall": 66,
      "abilities": [],
      "hometown": "",
      "state": ""
    },
    {
      "name": "DJ Cloyd",
      "firstName": "DJ",
      "lastName": "Cloyd",
      "position": "SS",
      "jerseyNumber": "20",
      "height": "6'1\"",
      "weight": 200,
      "class": "Jr",
      "archetype": "Coverage Specialist",
      "devTrait": "",
      "overall": 65,
      "abilities": [],
      "hometown": "",
      "state": ""
    },
    {
      "name": "Gavin Jones",
      "firstName": "Gavin",
      "lastName": "Jones",
      "position": "RG",
      "jerseyNumber": "77",
      "height": "6'6\"",
      "weight": 315,
      "class": "Fr",
      "archetype": "Well Rounded",
      "devTrait": "",
      "overall": 65,
      "abilities": [],
      "hometown": "",
      "state": ""
    },
    {
      "name": "Grayson Curtis",
      "firstName": "Grayson",
      "lastName": "Curtis",
      "position": "TE",
      "jerseyNumber": "42",
      "height": "6'1\"",
      "weight": 230,
      "class": "RS Jr",
      "archetype": "Pure Blocker",
      "devTrait": "",
      "overall": 65,
      "abilities": [],
      "hometown": "",
      "state": ""
    },
    {
      "name": "Elijah Harvey",
      "firstName": "Elijah",
      "lastName": "Harvey",
      "position": "RT",
      "jerseyNumber": "74",
      "height": "6'5\"",
      "weight": 320,
      "class": "RS So",
      "archetype": "Raw Strength",
      "devTrait": "",
      "overall": 64,
      "abilities": [],
      "hometown": "",
      "state": ""
    },
    {
      "name": "Bryan Sherman",
      "firstName": "Bryan",
      "lastName": "Sherman",
      "position": "SS",
      "jerseyNumber": "33",
      "height": "6'2\"",
      "weight": 217,
      "class": "So",
      "archetype": "Hybrid",
      "devTrait": "",
      "overall": 64,
      "abilities": [],
      "hometown": "",
      "state": ""
    },
    {
      "name": "James Long",
      "firstName": "James",
      "lastName": "Long",
      "position": "WR",
      "jerseyNumber": "27",
      "height": "5'11\"",
      "weight": 175,
      "class": "So",
      "archetype": "Speedster",
      "devTrait": "",
      "overall": 64,
      "abilities": [],
      "hometown": "",
      "state": ""
    },
    {
      "name": "Chance Barron",
      "firstName": "Chance",
      "lastName": "Barron",
      "position": "WILL",
      "jerseyNumber": "10",
      "height": "6'0\"",
      "weight": 215,
      "class": "Jr",
      "archetype": "Lurker",
      "devTrait": "",
      "overall": 64,
      "abilities": [],
      "hometown": "",
      "state": ""
    },
    {
      "name": "Sam Garcia",
      "firstName": "Sam",
      "lastName": "Garcia",
      "position": "C",
      "jerseyNumber": "64",
      "height": "6'4\"",
      "weight": 288,
      "weightFixed": true,
      "class": "Fr",
      "archetype": "Well Rounded",
      "devTrait": "",
      "overall": 64,
      "abilities": [],
      "hometown": "",
      "state": ""
    },
    {
      "name": "Sioeli Helu",
      "firstName": "Sioeli",
      "lastName": "Helu",
      "position": "C",
      "jerseyNumber": "58",
      "height": "6'2\"",
      "weight": 295,
      "class": "Sr",
      "archetype": "Well Rounded",
      "devTrait": "",
      "overall": 63,
      "abilities": [],
      "hometown": "",
      "state": ""
    },
    {
      "name": "Allen Ortiz",
      "firstName": "Allen",
      "lastName": "Ortiz",
      "position": "WR",
      "jerseyNumber": "81",
      "height": "6'3\"",
      "weight": 200,
      "class": "RS Sr",
      "archetype": "Speedster",
      "devTrait": "",
      "overall": 63,
      "abilities": [],
      "hometown": "",
      "state": ""
    },
    {
      "name": "Madison Schaub",
      "firstName": "Madison",
      "lastName": "Schaub",
      "position": "RG",
      "jerseyNumber": "60",
      "height": "6'2\"",
      "weight": 305,
      "class": "So",
      "archetype": "Agile",
      "devTrait": "",
      "overall": 62,
      "abilities": [],
      "hometown": "",
      "state": ""
    },
    {
      "name": "Merrick Becerra",
      "firstName": "Merrick",
      "lastName": "Becerra",
      "position": "LT",
      "jerseyNumber": "72",
      "height": "6'6\"",
      "weight": 315,
      "class": "So",
      "archetype": "Well Rounded",
      "devTrait": "",
      "overall": 62,
      "abilities": [],
      "hometown": "",
      "state": ""
    },
    {
      "name": "Jayden Bell",
      "firstName": "Jayden",
      "lastName": "Bell",
      "position": "WR",
      "jerseyNumber": "25",
      "height": "5'9\"",
      "weight": 170,
      "class": "RS So",
      "archetype": "Speedster",
      "devTrait": "",
      "overall": 62,
      "abilities": [],
      "hometown": "",
      "state": ""
    },
    {
      "name": "Tevin Russell",
      "firstName": "Tevin",
      "lastName": "Russell",
      "position": "MIKE",
      "jerseyNumber": "52",
      "height": "6'1\"",
      "weight": 242,
      "class": "Fr",
      "archetype": "Lurker",
      "devTrait": "",
      "overall": 61,
      "abilities": [],
      "hometown": "",
      "state": ""
    },
    {
      "name": "Zaiden Davis",
      "firstName": "Zaiden",
      "lastName": "Davis",
      "position": "SAM",
      "jerseyNumber": "34",
      "height": "6'2\"",
      "weight": 200,
      "class": "Fr",
      "archetype": "Lurker",
      "devTrait": "",
      "overall": 61,
      "abilities": [],
      "hometown": "",
      "state": ""
    },
    {
      "name": "Izeyah Wright",
      "firstName": "Izeyah",
      "lastName": "Wright",
      "position": "WR",
      "jerseyNumber": "80",
      "height": "6'4\"",
      "weight": 210,
      "class": "RS Fr",
      "archetype": "Contested Specialist",
      "devTrait": "",
      "overall": 60,
      "abilities": [],
      "hometown": "",
      "state": ""
    },
    {
      "name": "Bryant Jackson",
      "firstName": "Bryant",
      "lastName": "Jackson",
      "position": "MIKE",
      "jerseyNumber": "57",
      "height": "6'1\"",
      "weight": 230,
      "class": "RS Sr",
      "archetype": "Signal Caller",
      "devTrait": "",
      "overall": 56,
      "abilities": [],
      "hometown": "",
      "state": ""
    },
    {
      "name": "Jalen Brown",
      "firstName": "Jalen",
      "lastName": "Brown",
      "position": "WILL",
      "jerseyNumber": "47",
      "height": "6'2\"",
      "weight": 225,
      "class": "So",
      "archetype": "Signal Caller",
      "devTrait": "",
      "overall": 56,
      "abilities": [],
      "hometown": "",
      "state": ""
    }
  ]
}
